{"book":"DanTh","shard":"εμ","tokens":{"εμου":[{"book":"DanTh","ch":"2","v":"5","i":10,"w":"ἐμοῦ","lemma":"ἐμοῦ","morph":"C"},{"book":"DanTh","ch":"2","v":"6","i":18,"w":"ἐμοῦ","lemma":"ἐμοῦ","morph":"V.AAD2P"},{"book":"DanTh","ch":"2","v":"8","i":18,"w":"ἐμοῦ","lemma":"ἐμοῦ","morph":"V.AAS2P"},{"book":"DanTh","ch":"4","v":"2","i":8,"w":"ἐμοῦ","lemma":"ἐμοῦ","morph":"V.AAN"},{"book":"DanTh","ch":"4","v":"2","i":15,"w":"ἐμοῦ","lemma":"ἐμοῦ","morph":"N.NSF"},{"book":"DanTh","ch":"4","v":"6","i":2,"w":"ἐμοῦ","lemma":"ἐμοῦ","morph":"RA.APM"},{"book":"DanTh","ch":"8","v":"15","i":17,"w":"ἐμοῦ","lemma":"ἐμοῦ","morph":"P"},{"book":"DanTh","ch":"8","v":"18","i":6,"w":"ἐμοῦ","lemma":"ἐμοῦ","morph":"C"},{"book":"DanTh","ch":"9","v":"20","i":2,"w":"ἐμοῦ","lemma":"ἐμοῦ","morph":"RP.GS"},{"book":"DanTh","ch":"9","v":"21","i":2,"w":"ἐμοῦ","lemma":"ἐμοῦ","morph":"N.NSM"},{"book":"DanTh","ch":"9","v":"22","i":6,"w":"ἐμοῦ","lemma":"ἐμοῦ","morph":"N.ASF"},{"book":"DanTh","ch":"10","v":"7","i":12,"w":"ἐμοῦ","lemma":"ἐμοῦ","morph":"A.NSF"},{"book":"DanTh","ch":"10","v":"15","i":6,"w":"ἐμοῦ","lemma":"ἐμοῦ","morph":"RP.GS"},{"book":"DanTh","ch":"10","v":"16","i":23,"w":"ἐμοῦ","lemma":"ἐμοῦ","morph":"P"},{"book":"DanTh","ch":"10","v":"19","i":18,"w":"ἐμοῦ","lemma":"ἐμοῦ","morph":"C"},{"book":"DanTh","ch":"10","v":"21","i":15,"w":"ἐμοῦ","lemma":"ἐμοῦ","morph":"RP.GP"}],"εμοι":[{"book":"DanTh","ch":"2","v":"30","i":1,"w":"ἐμοὶ","lemma":"ἐμοί","morph":"RP.DS"},{"book":"DanTh","ch":"2","v":"30","i":9,"w":"ἐμοὶ","lemma":"ἐμοί","morph":"V.API3S"},{"book":"DanTh","ch":"7","v":"28","i":21,"w":"ἐμοί","lemma":"ἐμοί","morph":"V.AAI1S"},{"book":"DanTh","ch":"10","v":"8","i":15,"w":"ἐμοὶ","lemma":"ἐμοί","morph":"N.ASF"},{"book":"DanTh","ch":"10","v":"16","i":34,"w":"ἐμοί","lemma":"ἐμοί","morph":"RA.NSM"},{"book":"DanTh","ch":"10","v":"17","i":21,"w":"ἐμοὶ","lemma":"ἐμοί","morph":"C"},{"book":"DanTh","ch":"10","v":"17","i":28,"w":"ἐμοί","lemma":"ἐμοί","morph":"N.GSM"}],"εμεγαλυνεν":[{"book":"DanTh","ch":"2","v":"48","i":1,"w":"ἐμεγάλυνεν","lemma":"μεγαλύνω","morph":"C"}],"εμβληθησεται":[{"book":"DanTh","ch":"3","v":"6","i":9,"w":"ἐμβληθήσεται","lemma":"ἐμβάλλω","morph":"C"},{"book":"DanTh","ch":"3","v":"11","i":8,"w":"ἐμβληθήσεται","lemma":"ἐμβάλλω","morph":"V.PAI3P"},{"book":"DanTh","ch":"6","v":"8","i":38,"w":"ἐμβληθήσεται","lemma":"ἐμβάλλω","morph":"N.VSM"},{"book":"DanTh","ch":"6","v":"13","i":29,"w":"ἐμβληθήσεται","lemma":"ἐμβάλλω","morph":"RA.NSM"}],"εμβληθησεσθε":[{"book":"DanTh","ch":"3","v":"15","i":39,"w":"ἐμβληθήσεσθε","lemma":"ἐμβάλλω","morph":"C"}],"εμβαλειν":[{"book":"DanTh","ch":"3","v":"20","i":11,"w":"ἐμβαλεῖν","lemma":"ἐμβάλλω","morph":"D"}],"εμβαλοντεσ":[{"book":"DanTh","ch":"3","v":"46","i":4,"w":"ἐμβαλόντες","lemma":"ἐμβάλλω","morph":"N.ASF"}],"εμεγαλυνθη":[{"book":"DanTh","ch":"4","v":"11","i":0,"w":"ἐμεγαλύνθη","lemma":"μεγαλύνω","morph":"RD.GSN"},{"book":"DanTh","ch":"4","v":"22","i":11,"w":"ἐμεγαλύνθη","lemma":"μεγαλύνω","morph":"N.NSF"},{"book":"DanTh","ch":"8","v":"4","i":33,"w":"ἐμεγαλύνθη","lemma":"μεγαλύνω","morph":"N.GPM"},{"book":"DanTh","ch":"8","v":"8","i":5,"w":"ἐμεγαλύνθη","lemma":"μεγαλύνω","morph":"V.API3S"},{"book":"DanTh","ch":"8","v":"9","i":10,"w":"ἐμεγαλύνθη","lemma":"μεγαλύνω","morph":"C"},{"book":"DanTh","ch":"8","v":"10","i":0,"w":"ἐμεγαλύνθη","lemma":"μεγαλύνω","morph":"P"}],"εμεγαλυνθησ":[{"book":"DanTh","ch":"4","v":"22","i":4,"w":"ἐμεγαλύνθης","lemma":"μεγαλύνω","morph":"C"}],"εμεγαλυνθησαν":[{"book":"DanTh","ch":"4","v":"33","i":35,"w":"ἐμεγαλύνθησαν","lemma":"μεγαλύνω","morph":"P"}],"εμε":[{"book":"DanTh","ch":"4","v":"34","i":20,"w":"ἐμὲ","lemma":"ἐμέ","morph":"V.PAPDSM"},{"book":"DanTh","ch":"4","v":"36","i":8,"w":"ἐμέ","lemma":"ἐμέ","morph":"V.AAI1S"},{"book":"DanTh","ch":"4","v":"36","i":23,"w":"ἐμέ","lemma":"ἐμέ","morph":"RP.GS"}],"εμετρησεν":[{"book":"DanTh","ch":"5","v":"26","i":6,"w":"ἐμέτρησεν","lemma":"μετρέω","morph":"RD.ASF"}],"εμπροσθεν":[{"book":"DanTh","ch":"6","v":"11","i":46,"w":"ἔμπροσθεν","lemma":"ἔμπροσθεν","morph":"RA.ASM"},{"book":"DanTh","ch":"7","v":"7","i":38,"w":"ἔμπροσθεν","lemma":"ἔμπροσθεν","morph":"N.DPN"},{"book":"DanTh","ch":"7","v":"8","i":17,"w":"ἔμπροσθεν","lemma":"ἔμπροσθεν","morph":"N.NPM"},{"book":"DanTh","ch":"7","v":"10","i":3,"w":"ἔμπροσθεν","lemma":"ἔμπροσθεν","morph":"N.NPF"},{"book":"DanTh","ch":"7","v":"24","i":18,"w":"ἔμπροσθεν","lemma":"ἔμπροσθεν","morph":"RA.ASM"}],"εμαλακισθην":[{"book":"DanTh","ch":"8","v":"27","i":5,"w":"ἐμαλακίσθην","lemma":"μαλακίζομαι","morph":"RA.GSM"}],"εμφραξον":[{"book":"DanTh","ch":"12","v":"4","i":3,"w":"ἔμφραξον","lemma":"ἐμφράσσω","morph":"N.GSM"}],"εμπεφραγμενοι":[{"book":"DanTh","ch":"12","v":"9","i":5,"w":"ἐμπεφραγμένοι","lemma":"ἐμφράσσω","morph":"V.PAS3P"}]}}