{"book":"SusTh","shard":"#π","tokens":{"#πλουσιοσ":[{"book":"SusTh","ch":"1","v":"4","i":3,"w":"πλούσιος","lemma":"πλούσιος","morph":"N.DSM"}],"#παραδεισοσ":[{"book":"SusTh","ch":"1","v":"4","i":8,"w":"παράδεισος","lemma":"παράδεισος","morph":"V.IMI3P"},{"book":"SusTh","ch":"1","v":"7","i":14,"w":"παραδείσῳ","lemma":"παράδεισος","morph":"M.NDM"},{"book":"SusTh","ch":"1","v":"15","i":24,"w":"παραδείσῳ","lemma":"παράδεισος","morph":"D"},{"book":"SusTh","ch":"1","v":"17","i":14,"w":"παραδείσου","lemma":"παράδεισος","morph":"C"},{"book":"SusTh","ch":"1","v":"18","i":9,"w":"παραδείσου","lemma":"παράδεισος","morph":"RA.APN"},{"book":"SusTh","ch":"1","v":"20","i":6,"w":"παραδείσου","lemma":"παράδεισος","morph":"N.DSF"},{"book":"SusTh","ch":"1","v":"25","i":8,"w":"παραδείσου","lemma":"παράδεισος","morph":"N.DSM"},{"book":"SusTh","ch":"1","v":"26","i":7,"w":"παραδείσῳ","lemma":"παράδεισος","morph":"A.GSF"},{"book":"SusTh","ch":"1","v":"36","i":8,"w":"παραδείσῳ","lemma":"παράδεισος","morph":"V.AAI3S"},{"book":"SusTh","ch":"1","v":"36","i":20,"w":"παραδείσου","lemma":"παράδεισος","morph":"RD.ASF"},{"book":"SusTh","ch":"1","v":"38","i":7,"w":"παραδείσου","lemma":"παράδεισος","morph":"V.AAPNPM"}],"#προσ":[{"book":"SusTh","ch":"1","v":"4","i":14,"w":"πρὸς","lemma":"πρός","morph":"RD.ASM"},{"book":"SusTh","ch":"1","v":"6","i":8,"w":"πρὸς","lemma":"πρός","morph":"V.IAI3S"},{"book":"SusTh","ch":"1","v":"28","i":8,"w":"πρὸς","lemma":"πρός","morph":"N.NPM"},{"book":"SusTh","ch":"1","v":"37","i":2,"w":"πρὸς","lemma":"πρός","morph":"P"},{"book":"SusTh","ch":"1","v":"47","i":5,"w":"πρὸς","lemma":"πρός","morph":"RR.ASM"},{"book":"SusTh","ch":"1","v":"51","i":2,"w":"πρὸς","lemma":"πρός","morph":"C"},{"book":"SusTh","ch":"1","v":"52","i":13,"w":"πρὸς","lemma":"πρός","morph":"N.NPF"}],"#προσαγω":[{"book":"SusTh","ch":"1","v":"4","i":16,"w":"προσήγοντο","lemma":"προσάγω","morph":"A.GPM"},{"book":"SusTh","ch":"1","v":"56","i":4,"w":"προσαγαγεῖν","lemma":"προσάγω","morph":"C"}],"#πασ":[{"book":"SusTh","ch":"1","v":"4","i":24,"w":"πάντων","lemma":"πᾶς","morph":"N.NPM"},{"book":"SusTh","ch":"1","v":"6","i":10,"w":"πάντες","lemma":"πᾶς","morph":"N.NSM"},{"book":"SusTh","ch":"1","v":"30","i":12,"w":"πάντες","lemma":"πᾶς","morph":"A.NSF"},{"book":"SusTh","ch":"1","v":"33","i":6,"w":"πάντες","lemma":"πᾶς","morph":"N.NPM"},{"book":"SusTh","ch":"1","v":"42","i":18,"w":"πάντα","lemma":"πᾶς","morph":"RP.GS"},{"book":"SusTh","ch":"1","v":"47","i":2,"w":"πᾶς","lemma":"πᾶς","morph":"RA.NSM"},{"book":"SusTh","ch":"1","v":"50","i":2,"w":"πᾶς","lemma":"πᾶς","morph":"RA.NPM"},{"book":"SusTh","ch":"1","v":"60","i":2,"w":"πᾶσα","lemma":"πᾶς","morph":"N.DSM"},{"book":"SusTh","ch":"1","v":"63","i":22,"w":"πάντων","lemma":"πᾶς","morph":"C"}],"#πρεσβυτεροσ":[{"book":"SusTh","ch":"1","v":"5","i":3,"w":"πρεσβύτεροι","lemma":"πρεσβύτερος","morph":"RD.DSM"},{"book":"SusTh","ch":"1","v":"5","i":23,"w":"πρεσβυτέρων","lemma":"πρεσβύτερος","morph":"V.IAI3P"},{"book":"SusTh","ch":"1","v":"8","i":5,"w":"πρεσβύτεροι","lemma":"πρεσβύτερος","morph":"P"},{"book":"SusTh","ch":"1","v":"16","i":8,"w":"πρεσβύτεροι","lemma":"πρεσβύτερος","morph":"N.DPN"},{"book":"SusTh","ch":"1","v":"18","i":24,"w":"πρεσβυτέρους","lemma":"πρεσβύτερος","morph":"RA.APN"},{"book":"SusTh","ch":"1","v":"41","i":13,"w":"πρεσβυτέροις","lemma":"πρεσβύτερος","morph":"V.AAN"},{"book":"SusTh","ch":"1","v":"50","i":11,"w":"πρεσβύτεροι","lemma":"πρεσβύτερος","morph":"RP.DP"}],"#περι":[{"book":"SusTh","ch":"1","v":"5","i":12,"w":"περὶ","lemma":"περί","morph":"P"},{"book":"SusTh","ch":"1","v":"10","i":4,"w":"περὶ","lemma":"περί","morph":"RD.GPM"},{"book":"SusTh","ch":"1","v":"27","i":18,"w":"περὶ","lemma":"περί","morph":"RA.NSM"},{"book":"SusTh","ch":"1","v":"63","i":9,"w":"περὶ","lemma":"περί","morph":"N.GSM"}],"#προσκαρτερεω":[{"book":"SusTh","ch":"1","v":"6","i":1,"w":"προσεκαρτέρουν","lemma":"προσκαρτερέω","morph":"RD.APM"}],"#περιπατεω":[{"book":"SusTh","ch":"1","v":"7","i":11,"w":"περιεπάτει","lemma":"περιπατέω","morph":"V.IAI3P"},{"book":"SusTh","ch":"1","v":"8","i":10,"w":"περιπατοῦσαν","lemma":"περιπατέω","morph":"RA.ASM"},{"book":"SusTh","ch":"1","v":"36","i":4,"w":"περιπατούντων","lemma":"περιπατέω","morph":"P"}],"#παρατηρεω":[{"book":"SusTh","ch":"1","v":"12","i":1,"w":"παρετηροῦσαν","lemma":"παρατηρέω","morph":"A.NSM"},{"book":"SusTh","ch":"1","v":"15","i":4,"w":"παρατηρεῖν","lemma":"παρατηρέω","morph":"C"},{"book":"SusTh","ch":"1","v":"16","i":11,"w":"παρατηροῦντες","lemma":"παρατηρέω","morph":"RP.DS"}],"#πορευομαι":[{"book":"SusTh","ch":"1","v":"13","i":5,"w":"πορευθῶμεν","lemma":"πορεύομαι","morph":"C"}],"#ποτε":[{"book":"SusTh","ch":"1","v":"15","i":9,"w":"ποτε","lemma":"ποτέ","morph":"A.GPN"}],"#πλην":[{"book":"SusTh","ch":"1","v":"16","i":5,"w":"πλὴν","lemma":"πλήν","morph":"C"}],"#ποιεω":[{"book":"SusTh","ch":"1","v":"18","i":1,"w":"ἐποίησαν","lemma":"ποιέω","morph":"N.GSM"},{"book":"SusTh","ch":"1","v":"43","i":10,"w":"ποιήσασα","lemma":"ποιέω","morph":"V.AAI3S"},{"book":"SusTh","ch":"1","v":"52","i":24,"w":"ἐποίεις","lemma":"ποιέω","morph":"X"},{"book":"SusTh","ch":"1","v":"57","i":1,"w":"ἐποιεῖτε","lemma":"ποιέω","morph":"C"},{"book":"SusTh","ch":"1","v":"61","i":16,"w":"ἐποίησαν","lemma":"ποιέω","morph":"P"},{"book":"SusTh","ch":"1","v":"62","i":0,"w":"ποιῆσαι","lemma":"ποιέω","morph":"C"}],"#πλαγιοσ":[{"book":"SusTh","ch":"1","v":"18","i":14,"w":"πλαγίας","lemma":"πλάγιος","morph":"V.AAI3P"},{"book":"SusTh","ch":"1","v":"26","i":15,"w":"πλαγίας","lemma":"πλάγιος","morph":"V.AAI3P"}],"#προστασσω":[{"book":"SusTh","ch":"1","v":"18","i":18,"w":"προστεταγμένα","lemma":"προστάσσω","morph":"V.IAI3P"}],"#πρεσβυτησ":[{"book":"SusTh","ch":"1","v":"19","i":10,"w":"πρεσβῦται","lemma":"πρεσβύτης","morph":"N.NPF"},{"book":"SusTh","ch":"1","v":"24","i":10,"w":"πρεσβῦται","lemma":"πρεσβύτης","morph":"RA.APF"},{"book":"SusTh","ch":"1","v":"27","i":4,"w":"πρεσβῦται","lemma":"πρεσβύτης","morph":"C"},{"book":"SusTh","ch":"1","v":"28","i":16,"w":"πρεσβῦται","lemma":"πρεσβύτης","morph":"V.AAN"},{"book":"SusTh","ch":"1","v":"34","i":4,"w":"πρεσβῦται","lemma":"πρεσβύτης","morph":"P"},{"book":"SusTh","ch":"1","v":"36","i":3,"w":"πρεσβῦται","lemma":"πρεσβύτης","morph":"RD.NSF"},{"book":"SusTh","ch":"1","v":"61","i":5,"w":"πρεσβύτας","lemma":"πρεσβύτης","morph":"RD.GPM"}],"#παντοθεν":[{"book":"SusTh","ch":"1","v":"22","i":7,"w":"πάντοθεν","lemma":"πάντοθεν","morph":"V.PAI3S"}],"#πρασσω":[{"book":"SusTh","ch":"1","v":"22","i":12,"w":"πράξω","lemma":"πράσσω","morph":"D"},{"book":"SusTh","ch":"1","v":"22","i":19,"w":"πράξω","lemma":"πράσσω","morph":"V.PAI3S"},{"book":"SusTh","ch":"1","v":"23","i":4,"w":"πράξασαν","lemma":"πράσσω","morph":"D.P"}],"#πωποτε":[{"book":"SusTh","ch":"1","v":"27","i":13,"w":"πώποτε","lemma":"πώποτε","morph":"V.AMI3S"}],"#πληρησ":[{"book":"SusTh","ch":"1","v":"28","i":17,"w":"πλήρεις","lemma":"πλήρης","morph":"RD.ASF"}],"#παρανομοσ":[{"book":"SusTh","ch":"1","v":"32","i":2,"w":"παράνομοι","lemma":"παράνομος","morph":"V.APS3P"}],"#παρα":[{"book":"SusTh","ch":"1","v":"33","i":3,"w":"παρ᾿","lemma":"παρά","morph":"X"},{"book":"SusTh","ch":"1","v":"55","i":16,"w":"παρὰ","lemma":"παρά","morph":"RD.ASM"}],"#πειθω":[{"book":"SusTh","ch":"1","v":"35","i":12,"w":"πεποιθυῖα","lemma":"πείθω","morph":"V.PAPGPM"}],"#παιδισκη":[{"book":"SusTh","ch":"1","v":"36","i":14,"w":"παιδισκῶν","lemma":"παιδίσκη","morph":"V.AAI3S"},{"book":"SusTh","ch":"1","v":"36","i":24,"w":"παιδίσκας","lemma":"παιδίσκη","morph":"V.XMPNSM"}],"#πιστευω":[{"book":"SusTh","ch":"1","v":"41","i":8,"w":"ἐπίστευσεν","lemma":"πιστεύω","morph":"C"}],"#πριν":[{"book":"SusTh","ch":"1","v":"42","i":19,"w":"πρὶν","lemma":"πρίν","morph":"V.AAI3P"}],"#πονηρευω":[{"book":"SusTh","ch":"1","v":"43","i":14,"w":"ἐπονηρεύσαντο","lemma":"πονηρεύω","morph":"RD.GSF"},{"book":"SusTh","ch":"1","v":"61","i":20,"w":"ἐπονηρεύσαντο","lemma":"πονηρεύω","morph":"C"}],"#πνευμα":[{"book":"SusTh","ch":"1","v":"45","i":8,"w":"πνεῦμα","lemma":"πνεῦμα","morph":"C"}],"#παιδαριον":[{"book":"SusTh","ch":"1","v":"45","i":11,"w":"παιδαρίου","lemma":"παιδάριον","morph":"A.DSF"}],"#πρεσβειον":[{"book":"SusTh","ch":"1","v":"50","i":26,"w":"πρεσβεῖον","lemma":"πρεσβεῖον","morph":"P"}],"#παλαιοω":[{"book":"SusTh","ch":"1","v":"52","i":15,"w":"πεπαλαιωμένε","lemma":"παλαιόω","morph":"RR.APF"}],"#προτερον":[{"book":"SusTh","ch":"1","v":"52","i":26,"w":"πρότερον","lemma":"πρότερον","morph":"V.PAPNSM"}],"#πρινοσ":[{"book":"SusTh","ch":"1","v":"58","i":15,"w":"πρῖνον","lemma":"πρῖνος","morph":"RP.NS"}],"#πριω":[{"book":"SusTh","ch":"1","v":"59","i":21,"w":"πρίσαι","lemma":"πρίω","morph":"A.NSF"}],"#πλησιον":[{"book":"SusTh","ch":"1","v":"61","i":22,"w":"πλησίον","lemma":"πλησίον","morph":"RD.APM"}],"#πραγμα":[{"book":"SusTh","ch":"1","v":"63","i":29,"w":"πρᾶγμα","lemma":"πρᾶγμα","morph":"P"}]}}