{"book":"TobBA","shard":"κο","tokens":{"κοιλια":[{"book":"TobBA","ch":"4","v":"4","i":10,"w":"κοιλίᾳ","lemma":"κοιλία","morph":"N.DSF"}],"κοινωσ":[{"book":"TobBA","ch":"5","v":"14","i":44,"w":"κοινῶς","lemma":"κοινῶς","morph":"D"},{"book":"TobBA","ch":"9","v":"6","i":2,"w":"κοινῶς","lemma":"κοινῶς","morph":"D"}],"κορασιον":[{"book":"TobBA","ch":"6","v":"12","i":25,"w":"κοράσιον","lemma":"κοράσιον","morph":"N.NSN"},{"book":"TobBA","ch":"6","v":"14","i":11,"w":"κοράσιον","lemma":"κοράσιον","morph":"N.ASN"}],"κομιζου":[{"book":"TobBA","ch":"7","v":"12","i":17,"w":"κομίζου","lemma":"κομίζω","morph":"V.PMD2S"},{"book":"TobBA","ch":"7","v":"13","i":23,"w":"κομίζου","lemma":"κομίζω","morph":"V.PMD2S"}],"κομισαι":[{"book":"TobBA","ch":"9","v":"2","i":18,"w":"κόμισαί","lemma":"κομίζω","morph":"V.AMD2S"}]}}