{"book":"Bar","shard":"πα","tokens":{"παντοσ":[{"book":"Bar","ch":"1","v":"3","i":18,"w":"παντὸς","lemma":"πᾶς","morph":"C"},{"book":"Bar","ch":"1","v":"4","i":17,"w":"παντὸς","lemma":"πᾶς","morph":"RA.GPM"},{"book":"Bar","ch":"2","v":"2","i":3,"w":"παντὸς","lemma":"πᾶς","morph":"RA.APN"}],"παντων":[{"book":"Bar","ch":"1","v":"4","i":24,"w":"πάντων","lemma":"πᾶς","morph":"C"}],"παντα":[{"book":"Bar","ch":"1","v":"7","i":18,"w":"πάντα","lemma":"πᾶς","morph":"N.DSF"},{"book":"Bar","ch":"2","v":"7","i":5,"w":"πάντα","lemma":"πᾶς","morph":"D"},{"book":"Bar","ch":"2","v":"9","i":16,"w":"πάντα","lemma":"πᾶς","morph":"D"},{"book":"Bar","ch":"2","v":"27","i":14,"w":"πάντα","lemma":"πᾶς","morph":"N.DSF"},{"book":"Bar","ch":"3","v":"32","i":4,"w":"πάντα","lemma":"πᾶς","morph":"RA.NSM"}],"πατρασιν":[{"book":"Bar","ch":"1","v":"16","i":18,"w":"πατράσιν","lemma":"πατήρ","morph":"RD.DSM"},{"book":"Bar","ch":"2","v":"6","i":10,"w":"πατράσιν","lemma":"πατήρ","morph":"N.NSF"},{"book":"Bar","ch":"2","v":"21","i":20,"w":"πατράσιν","lemma":"πατήρ","morph":"N.GSM"},{"book":"Bar","ch":"2","v":"34","i":9,"w":"πατράσιν","lemma":"πατήρ","morph":"RA.DSM"}],"πατερασ":[{"book":"Bar","ch":"1","v":"19","i":7,"w":"πατέρας","lemma":"πατήρ","morph":"N.GSF"},{"book":"Bar","ch":"1","v":"20","i":21,"w":"πατέρας","lemma":"πατήρ","morph":"V.PAPASF"}],"παιδι":[{"book":"Bar","ch":"1","v":"20","i":14,"w":"παιδὶ","lemma":"παῖς","morph":"RP.GP"},{"book":"Bar","ch":"3","v":"37","i":9,"w":"παιδὶ","lemma":"παῖς","morph":"P"}],"παντασ":[{"book":"Bar","ch":"1","v":"21","i":10,"w":"πάντας","lemma":"πᾶς","morph":"RP.AP"}],"πασαισ":[{"book":"Bar","ch":"2","v":"4","i":4,"w":"πάσαις","lemma":"πᾶς","morph":"C"}],"πασι":[{"book":"Bar","ch":"2","v":"4","i":16,"w":"πᾶσι","lemma":"πᾶς","morph":"N.NSM"}],"πασιν":[{"book":"Bar","ch":"2","v":"12","i":8,"w":"πᾶσιν","lemma":"πᾶς","morph":"P"}],"πασα":[{"book":"Bar","ch":"2","v":"15","i":2,"w":"πᾶσα","lemma":"πᾶς","morph":"RP.GP"},{"book":"Bar","ch":"2","v":"23","i":20,"w":"πᾶσα","lemma":"πᾶς","morph":"D"}],"πατερων":[{"book":"Bar","ch":"2","v":"19","i":6,"w":"πατέρων","lemma":"πατήρ","morph":"RA.ASM"},{"book":"Bar","ch":"2","v":"24","i":34,"w":"πατέρων","lemma":"πατήρ","morph":"V.PAI3S"},{"book":"Bar","ch":"2","v":"33","i":17,"w":"πατέρων","lemma":"πατήρ","morph":"RD.APM"},{"book":"Bar","ch":"3","v":"5","i":3,"w":"πατέρων","lemma":"πατήρ","morph":"RP.GS"},{"book":"Bar","ch":"3","v":"7","i":29,"w":"πατέρων","lemma":"πατήρ","morph":"D"},{"book":"Bar","ch":"3","v":"8","i":23,"w":"πατέρων","lemma":"πατήρ","morph":"V.PAD2S"}],"παιδων":[{"book":"Bar","ch":"2","v":"20","i":16,"w":"παίδων","lemma":"παῖς","morph":"V.AAD2P"},{"book":"Bar","ch":"2","v":"24","i":20,"w":"παίδων","lemma":"παῖς","morph":"N.GPM"}],"παγετω":[{"book":"Bar","ch":"2","v":"25","i":10,"w":"παγετῷ","lemma":"παγετός","morph":"P"}],"πασαν":[{"book":"Bar","ch":"2","v":"27","i":9,"w":"πᾶσαν","lemma":"πᾶς","morph":"RA.ASM"},{"book":"Bar","ch":"3","v":"7","i":27,"w":"πᾶσαν","lemma":"πᾶς","morph":"I"},{"book":"Bar","ch":"3","v":"37","i":1,"w":"πᾶσαν","lemma":"πᾶς","morph":"N.DSM"}],"παιδοσ":[{"book":"Bar","ch":"2","v":"28","i":4,"w":"παιδός","lemma":"παῖς","morph":"V.AAN"}],"παντοκρατωρ":[{"book":"Bar","ch":"3","v":"1","i":1,"w":"παντοκράτωρ","lemma":"παντοκράτωρ","morph":"N.ASN"},{"book":"Bar","ch":"3","v":"4","i":1,"w":"παντοκράτωρ","lemma":"παντοκράτωρ","morph":"RA.GPM"}],"πασασ":[{"book":"Bar","ch":"3","v":"8","i":20,"w":"πάσας","lemma":"πᾶς","morph":"N.GSM"}],"παρα":[{"book":"Bar","ch":"3","v":"28","i":2,"w":"παρὰ","lemma":"παρά","morph":"N.ASF"},{"book":"Bar","ch":"4","v":"9","i":6,"w":"παρὰ","lemma":"παρά","morph":"N.GSF"},{"book":"Bar","ch":"4","v":"22","i":13,"w":"παρὰ","lemma":"παρά","morph":"RP.DP"},{"book":"Bar","ch":"4","v":"22","i":24,"w":"παρὰ","lemma":"παρά","morph":"P"},{"book":"Bar","ch":"4","v":"24","i":15,"w":"παρὰ","lemma":"παρά","morph":"P"},{"book":"Bar","ch":"4","v":"25","i":3,"w":"παρὰ","lemma":"παρά","morph":"RA.NSM"},{"book":"Bar","ch":"4","v":"35","i":4,"w":"παρὰ","lemma":"παρά","morph":"P"},{"book":"Bar","ch":"4","v":"36","i":9,"w":"παρὰ","lemma":"παρά","morph":"N.NPM"},{"book":"Bar","ch":"5","v":"1","i":15,"w":"παρὰ","lemma":"παρά","morph":"RA.ASF"},{"book":"Bar","ch":"5","v":"2","i":4,"w":"παρὰ","lemma":"παρά","morph":"RA.ASF"},{"book":"Bar","ch":"5","v":"4","i":5,"w":"παρὰ","lemma":"παρά","morph":"C"},{"book":"Bar","ch":"5","v":"6","i":2,"w":"παρὰ","lemma":"παρά","morph":"RD.APM"}],"παρεσμεν":[{"book":"Bar","ch":"3","v":"35","i":4,"w":"πάρεσμεν","lemma":"πάρειμι","morph":"RA.NSM"}],"παντεσ":[{"book":"Bar","ch":"4","v":"1","i":15,"w":"πάντες","lemma":"πᾶς","morph":"V.PAPNPM"}],"παροργισαι":[{"book":"Bar","ch":"4","v":"6","i":9,"w":"παροργίσαι","lemma":"παροργίζω","morph":"X"}],"παρεδοθητε":[{"book":"Bar","ch":"4","v":"6","i":13,"w":"παρεδόθητε","lemma":"παραδίδωμι","morph":"V.AAPNPM"}],"παρωξυνατε":[{"book":"Bar","ch":"4","v":"7","i":0,"w":"παρωξύνατε","lemma":"παροξύνω","morph":"D"}],"παροικοι":[{"book":"Bar","ch":"4","v":"9","i":13,"w":"πάροικοι","lemma":"πάροικος","morph":"V.AAI3P"},{"book":"Bar","ch":"4","v":"14","i":2,"w":"πάροικοι","lemma":"πάροικος","morph":"RP.GS"},{"book":"Bar","ch":"4","v":"24","i":5,"w":"πάροικοι","lemma":"πάροικος","morph":"A.DSM"}],"παιδειασ":[{"book":"Bar","ch":"4","v":"13","i":12,"w":"παιδείας","lemma":"παιδεία","morph":"N.GSF"}],"παιδιον":[{"book":"Bar","ch":"4","v":"15","i":15,"w":"παιδίον","lemma":"παιδίον","morph":"C"}],"παρακαλεσει":[{"book":"Bar","ch":"4","v":"30","i":2,"w":"παρακαλέσει","lemma":"παρακαλέω","morph":"V.AAPNPM"}],"παση":[{"book":"Bar","ch":"5","v":"3","i":7,"w":"πάσῃ","lemma":"πᾶς","morph":"N.NSN"}],"παν":[{"book":"Bar","ch":"5","v":"7","i":5,"w":"πᾶν","lemma":"πᾶς","morph":"V.PMN"},{"book":"Bar","ch":"5","v":"8","i":6,"w":"πᾶν","lemma":"πᾶς","morph":"V.FMI3S"}],"παρ᾿":[{"book":"Bar","ch":"5","v":"9","i":17,"w":"παρ᾿","lemma":"παρά","morph":"RA.APM"}]}}