{"book":"Isa","shard":"ρη","tokens":{"ρημα":[{"book":"Isa","ch":"8","v":"20","i":10,"w":"ῥῆμα","lemma":"ῥῆμα","morph":"P"},{"book":"Isa","ch":"14","v":"28","i":9,"w":"ῥῆμα","lemma":"ῥῆμα","morph":"X"},{"book":"Isa","ch":"15","v":"1","i":1,"w":"ῥῆμα","lemma":"ῥῆμα","morph":"N.ASF"},{"book":"Isa","ch":"16","v":"13","i":2,"w":"ῥῆμα","lemma":"ῥῆμα","morph":"V.AAI3S"},{"book":"Isa","ch":"17","v":"1","i":1,"w":"ῥῆμα","lemma":"ῥῆμα","morph":"N.GPF"},{"book":"Isa","ch":"22","v":"1","i":1,"w":"ῥῆμα","lemma":"ῥῆμα","morph":"C"},{"book":"Isa","ch":"38","v":"7","i":12,"w":"ῥῆμα","lemma":"ῥῆμα","morph":"RA.NSM"},{"book":"Isa","ch":"40","v":"8","i":2,"w":"ῥῆμα","lemma":"ῥῆμα","morph":"P"},{"book":"Isa","ch":"55","v":"11","i":3,"w":"ῥῆμά","lemma":"ῥῆμα","morph":"RP.GS"},{"book":"Isa","ch":"58","v":"9","i":21,"w":"ῥῆμα","lemma":"ῥῆμα","morph":"N.GSF"},{"book":"Isa","ch":"66","v":"5","i":2,"w":"ῥῆμα","lemma":"ῥῆμα","morph":"N.NPM"}],"ρηματα":[{"book":"Isa","ch":"29","v":"11","i":5,"w":"ῥήματα","lemma":"ῥῆμα","morph":"V.XMPGSN"},{"book":"Isa","ch":"42","v":"16","i":29,"w":"ῥήματα","lemma":"ῥῆμα","morph":"V.API3P"},{"book":"Isa","ch":"44","v":"26","i":2,"w":"ῥήματα","lemma":"ῥῆμα","morph":"RD.GSM"},{"book":"Isa","ch":"59","v":"21","i":19,"w":"ῥήματα","lemma":"ῥῆμα","morph":"D"}],"ρηξατωσαν":[{"book":"Isa","ch":"49","v":"13","i":6,"w":"ῥηξάτωσαν","lemma":"ῥήγνυμι","morph":"C"}],"ρηξατω":[{"book":"Isa","ch":"52","v":"9","i":0,"w":"ῥηξάτω","lemma":"ῥήγνυμι","morph":"N.NSM"}],"ρηξον":[{"book":"Isa","ch":"54","v":"1","i":5,"w":"ῥῆξον","lemma":"ῥήγνυμι","morph":"RA.NPN"}]}}