{"book":"1Kgs","shard":"πα","tokens":{"παιδεσ":[{"book":"1Kgs","ch":"1","v":"2","i":3,"w":"παῖδες","lemma":"παῖς","morph":"N.NPM"},{"book":"1Kgs","ch":"10","v":"8","i":6,"w":"παῖδές","lemma":"παῖς","morph":"N.NPM"},{"book":"1Kgs","ch":"10","v":"13","i":35,"w":"παῖδες","lemma":"παῖς","morph":"N.NPM"},{"book":"1Kgs","ch":"10","v":"22c","i":17,"w":"παῖδες","lemma":"παῖς","morph":"N.NPM"},{"book":"1Kgs","ch":"21","v":"23","i":2,"w":"παῖδες","lemma":"παῖς","morph":"N.NPM"}],"παρθενον":[{"book":"1Kgs","ch":"1","v":"2","i":11,"w":"παρθένον","lemma":"παρθένος","morph":"N.ASF"}],"παραστησεται":[{"book":"1Kgs","ch":"1","v":"2","i":14,"w":"παραστήσεται","lemma":"παρίστημι","morph":"V.FMI3S"}],"παντοσ":[{"book":"1Kgs","ch":"1","v":"3","i":5,"w":"παντὸς","lemma":"πᾶς","morph":"A.GSN"},{"book":"1Kgs","ch":"1","v":"20","i":7,"w":"παντὸς","lemma":"πᾶς","morph":"A.GSM"},{"book":"1Kgs","ch":"5","v":"27","i":6,"w":"παντὸς","lemma":"πᾶς","morph":"A.GSM"},{"book":"1Kgs","ch":"6","v":"22","i":8,"w":"παντὸς","lemma":"πᾶς","morph":"A.GSM"},{"book":"1Kgs","ch":"14","v":"23","i":14,"w":"παντὸς","lemma":"πᾶς","morph":"A.GSN"}],"παρατρεχειν":[{"book":"1Kgs","ch":"1","v":"5","i":17,"w":"παρατρέχειν","lemma":"παρατρέχω","morph":"V.PAN"}],"πατηρ":[{"book":"1Kgs","ch":"1","v":"6","i":5,"w":"πατὴρ","lemma":"πατήρ","morph":"N.NSM"},{"book":"1Kgs","ch":"2","v":"26","i":47,"w":"πατήρ","lemma":"πατήρ","morph":"N.NSM"},{"book":"1Kgs","ch":"2","v":"32","i":29,"w":"πατήρ","lemma":"πατήρ","morph":"N.NSM"},{"book":"1Kgs","ch":"3","v":"14","i":19,"w":"πατήρ","lemma":"πατήρ","morph":"N.NSM"},{"book":"1Kgs","ch":"7","v":"2","i":11,"w":"πατὴρ","lemma":"πατήρ","morph":"N.NSM"},{"book":"1Kgs","ch":"9","v":"4","i":10,"w":"πατήρ","lemma":"πατήρ","morph":"N.NSM"},{"book":"1Kgs","ch":"11","v":"8","i":14,"w":"πατὴρ","lemma":"πατήρ","morph":"N.NSM"},{"book":"1Kgs","ch":"11","v":"33","i":40,"w":"πατὴρ","lemma":"πατήρ","morph":"N.NSM"},{"book":"1Kgs","ch":"12","v":"4","i":1,"w":"πατήρ","lemma":"πατήρ","morph":"N.NSM"},{"book":"1Kgs","ch":"12","v":"9","i":24,"w":"πατήρ","lemma":"πατήρ","morph":"N.NSM"},{"book":"1Kgs","ch":"12","v":"10","i":27,"w":"πατήρ","lemma":"πατήρ","morph":"N.NSM"},{"book":"1Kgs","ch":"12","v":"11","i":3,"w":"πατήρ","lemma":"πατήρ","morph":"N.NSM"},{"book":"1Kgs","ch":"12","v":"11","i":16,"w":"πατήρ","lemma":"πατήρ","morph":"N.NSM"},{"book":"1Kgs","ch":"12","v":"14","i":11,"w":"πατήρ","lemma":"πατήρ","morph":"N.NSM"},{"book":"1Kgs","ch":"12","v":"14","i":24,"w":"πατήρ","lemma":"πατήρ","morph":"N.NSM"},{"book":"1Kgs","ch":"12","v":"24p","i":9,"w":"πατήρ","lemma":"πατήρ","morph":"N.NSM"},{"book":"1Kgs","ch":"12","v":"24r","i":53,"w":"πατήρ","lemma":"πατήρ","morph":"N.NSM"},{"book":"1Kgs","ch":"13","v":"12","i":5,"w":"πατὴρ","lemma":"πατήρ","morph":"N.NSM"},{"book":"1Kgs","ch":"15","v":"11","i":10,"w":"πατὴρ","lemma":"πατήρ","morph":"N.NSM"},{"book":"1Kgs","ch":"21","v":"34","i":9,"w":"πατήρ","lemma":"πατήρ","morph":"N.NSM"},{"book":"1Kgs","ch":"21","v":"34","i":26,"w":"πατήρ","lemma":"πατήρ","morph":"N.NSM"}],"παντασ":[{"book":"1Kgs","ch":"1","v":"9","i":20,"w":"πάντας","lemma":"πᾶς","morph":"A.APM"},{"book":"1Kgs","ch":"1","v":"9","i":25,"w":"πάντας","lemma":"πᾶς","morph":"A.APM"},{"book":"1Kgs","ch":"1","v":"19","i":11,"w":"πάντας","lemma":"πᾶς","morph":"A.APM"},{"book":"1Kgs","ch":"1","v":"25","i":14,"w":"πάντας","lemma":"πᾶς","morph":"A.APM"},{"book":"1Kgs","ch":"2","v":"35b","i":14,"w":"πάντας","lemma":"πᾶς","morph":"A.APM"},{"book":"1Kgs","ch":"5","v":"10","i":12,"w":"πάντας","lemma":"πᾶς","morph":"A.APM"},{"book":"1Kgs","ch":"5","v":"11","i":3,"w":"πάντας","lemma":"πᾶς","morph":"A.APM"},{"book":"1Kgs","ch":"6","v":"29","i":1,"w":"πάντας","lemma":"πᾶς","morph":"A.APM"},{"book":"1Kgs","ch":"8","v":"1","i":23,"w":"πάντας","lemma":"πᾶς","morph":"A.APM"},{"book":"1Kgs","ch":"9","v":"7","i":32,"w":"πάντας","lemma":"πᾶς","morph":"A.APM"},{"book":"1Kgs","ch":"10","v":"3","i":4,"w":"πάντας","lemma":"πᾶς","morph":"A.APM"},{"book":"1Kgs","ch":"10","v":"23","i":4,"w":"πάντας","lemma":"πᾶς","morph":"A.APM"},{"book":"1Kgs","ch":"14","v":"26","i":2,"w":"πάντας","lemma":"πᾶς","morph":"A.APM"},{"book":"1Kgs","ch":"16","v":"25","i":10,"w":"πάντας","lemma":"πᾶς","morph":"A.APM"},{"book":"1Kgs","ch":"16","v":"30","i":9,"w":"πάντας","lemma":"πᾶς","morph":"A.APM"},{"book":"1Kgs","ch":"16","v":"33","i":19,"w":"πάντας","lemma":"πᾶς","morph":"A.APM"},{"book":"1Kgs","ch":"18","v":"20","i":8,"w":"πάντας","lemma":"πᾶς","morph":"A.APM"},{"book":"1Kgs","ch":"18","v":"21","i":4,"w":"πάντας","lemma":"πᾶς","morph":"A.APM"},{"book":"1Kgs","ch":"21","v":"7","i":5,"w":"πάντας","lemma":"πᾶς","morph":"A.APM"},{"book":"1Kgs","ch":"21","v":"21","i":6,"w":"πάντας","lemma":"πᾶς","morph":"A.APM"},{"book":"1Kgs","ch":"22","v":"6","i":5,"w":"πάντας","lemma":"πᾶς","morph":"A.APM"}],"παιδασ":[{"book":"1Kgs","ch":"1","v":"9","i":29,"w":"παῖδας","lemma":"παῖς","morph":"N.APM"},{"book":"1Kgs","ch":"5","v":"15","i":6,"w":"παῖδας","lemma":"παῖς","morph":"N.APM"},{"book":"1Kgs","ch":"16","v":"28g","i":9,"w":"παῖδάς","lemma":"παῖς","morph":"N.APM"},{"book":"1Kgs","ch":"21","v":"6","i":7,"w":"παῖδάς","lemma":"παῖς","morph":"N.APM"},{"book":"1Kgs","ch":"22","v":"3","i":6,"w":"παῖδας","lemma":"παῖς","morph":"N.APM"}],"πατερων":[{"book":"1Kgs","ch":"1","v":"21","i":12,"w":"πατέρων","lemma":"πατήρ","morph":"N.GPM"},{"book":"1Kgs","ch":"2","v":"10","i":5,"w":"πατέρων","lemma":"πατήρ","morph":"N.GPM"},{"book":"1Kgs","ch":"8","v":"21","i":17,"w":"πατέρων","lemma":"πατήρ","morph":"N.GPM"},{"book":"1Kgs","ch":"8","v":"57","i":11,"w":"πατέρων","lemma":"πατήρ","morph":"N.GPM"},{"book":"1Kgs","ch":"11","v":"21","i":10,"w":"πατέρων","lemma":"πατήρ","morph":"N.GPM"},{"book":"1Kgs","ch":"11","v":"43","i":5,"w":"πατέρων","lemma":"πατήρ","morph":"N.GPM"},{"book":"1Kgs","ch":"11","v":"43","i":60,"w":"πατέρων","lemma":"πατήρ","morph":"N.GPM"},{"book":"1Kgs","ch":"12","v":"24a","i":7,"w":"πατέρων","lemma":"πατήρ","morph":"N.GPM"},{"book":"1Kgs","ch":"12","v":"24a","i":13,"w":"πατέρων","lemma":"πατήρ","morph":"N.GPM"},{"book":"1Kgs","ch":"13","v":"22","i":34,"w":"πατέρων","lemma":"πατήρ","morph":"N.GPM"},{"book":"1Kgs","ch":"14","v":"31","i":5,"w":"πατέρων","lemma":"πατήρ","morph":"N.GPM"},{"book":"1Kgs","ch":"14","v":"31","i":11,"w":"πατέρων","lemma":"πατήρ","morph":"N.GPM"},{"book":"1Kgs","ch":"15","v":"8","i":5,"w":"πατέρων","lemma":"πατήρ","morph":"N.GPM"},{"book":"1Kgs","ch":"15","v":"8","i":19,"w":"πατέρων","lemma":"πατήρ","morph":"N.GPM"},{"book":"1Kgs","ch":"15","v":"24","i":7,"w":"πατέρων","lemma":"πατήρ","morph":"N.GPM"},{"book":"1Kgs","ch":"16","v":"6","i":5,"w":"πατέρων","lemma":"πατήρ","morph":"N.GPM"},{"book":"1Kgs","ch":"16","v":"28","i":5,"w":"πατέρων","lemma":"πατήρ","morph":"N.GPM"},{"book":"1Kgs","ch":"16","v":"28h","i":5,"w":"πατέρων","lemma":"πατήρ","morph":"N.GPM"},{"book":"1Kgs","ch":"16","v":"28h","i":11,"w":"πατέρων","lemma":"πατήρ","morph":"N.GPM"},{"book":"1Kgs","ch":"20","v":"3","i":13,"w":"πατέρων","lemma":"πατήρ","morph":"N.GPM"},{"book":"1Kgs","ch":"20","v":"6","i":32,"w":"πατέρων","lemma":"πατήρ","morph":"N.GPM"},{"book":"1Kgs","ch":"22","v":"40","i":5,"w":"πατέρων","lemma":"πατήρ","morph":"N.GPM"},{"book":"1Kgs","ch":"22","v":"51","i":5,"w":"πατέρων","lemma":"πατήρ","morph":"N.GPM"}],"πασησ":[{"book":"1Kgs","ch":"1","v":"29","i":14,"w":"πάσης","lemma":"πᾶς","morph":"A.GSF"},{"book":"1Kgs","ch":"2","v":"2","i":5,"w":"πάσης","lemma":"πᾶς","morph":"A.GSF"},{"book":"1Kgs","ch":"8","v":"22","i":9,"w":"πάσης","lemma":"πᾶς","morph":"A.GSF"},{"book":"1Kgs","ch":"15","v":"20","i":34,"w":"πάσης","lemma":"πᾶς","morph":"A.GSF"}],"πασ":[{"book":"1Kgs","ch":"1","v":"39","i":22,"w":"πᾶς","lemma":"πᾶς","morph":"A.NSM"},{"book":"1Kgs","ch":"1","v":"40","i":2,"w":"πᾶς","lemma":"πᾶς","morph":"A.NSM"},{"book":"1Kgs","ch":"2","v":"15","i":14,"w":"πᾶς","lemma":"πᾶς","morph":"A.NSM"},{"book":"1Kgs","ch":"3","v":"28","i":2,"w":"πᾶς","lemma":"πᾶς","morph":"A.NSM"},{"book":"1Kgs","ch":"4","v":"12","i":7,"w":"πᾶς","lemma":"πᾶς","morph":"A.NSM"},{"book":"1Kgs","ch":"8","v":"5","i":4,"w":"πᾶς","lemma":"πᾶς","morph":"A.NSM"},{"book":"1Kgs","ch":"8","v":"65","i":10,"w":"πᾶς","lemma":"πᾶς","morph":"A.NSM"},{"book":"1Kgs","ch":"9","v":"8","i":6,"w":"πᾶς","lemma":"πᾶς","morph":"A.NSM"},{"book":"1Kgs","ch":"11","v":"16","i":7,"w":"πᾶς","lemma":"πᾶς","morph":"A.NSM"},{"book":"1Kgs","ch":"12","v":"1","i":10,"w":"πᾶς","lemma":"πᾶς","morph":"A.NSM"},{"book":"1Kgs","ch":"12","v":"12","i":2,"w":"πᾶς","lemma":"πᾶς","morph":"A.NSM"},{"book":"1Kgs","ch":"12","v":"16","i":2,"w":"πᾶς","lemma":"πᾶς","morph":"A.NSM"},{"book":"1Kgs","ch":"12","v":"18","i":13,"w":"πᾶς","lemma":"πᾶς","morph":"A.NSM"},{"book":"1Kgs","ch":"12","v":"20","i":4,"w":"πᾶς","lemma":"πᾶς","morph":"A.NSM"},{"book":"1Kgs","ch":"12","v":"24t","i":2,"w":"πᾶς","lemma":"πᾶς","morph":"A.NSM"},{"book":"1Kgs","ch":"12","v":"24u","i":2,"w":"πᾶς","lemma":"πᾶς","morph":"A.NSM"},{"book":"1Kgs","ch":"15","v":"27","i":21,"w":"πᾶς","lemma":"πᾶς","morph":"A.NSM"},{"book":"1Kgs","ch":"16","v":"17","i":4,"w":"πᾶς","lemma":"πᾶς","morph":"A.NSM"},{"book":"1Kgs","ch":"18","v":"24","i":28,"w":"πᾶς","lemma":"πᾶς","morph":"A.NSM"},{"book":"1Kgs","ch":"18","v":"30","i":11,"w":"πᾶς","lemma":"πᾶς","morph":"A.NSM"},{"book":"1Kgs","ch":"18","v":"36","i":26,"w":"πᾶς","lemma":"πᾶς","morph":"A.NSM"},{"book":"1Kgs","ch":"18","v":"39","i":2,"w":"πᾶς","lemma":"πᾶς","morph":"A.NSM"},{"book":"1Kgs","ch":"21","v":"1","i":22,"w":"πᾶς","lemma":"πᾶς","morph":"A.NSM"},{"book":"1Kgs","ch":"21","v":"8","i":6,"w":"πᾶς","lemma":"πᾶς","morph":"A.NSM"}],"παντεσ":[{"book":"1Kgs","ch":"1","v":"41","i":4,"w":"πάντες","lemma":"πᾶς","morph":"A.NPM"},{"book":"1Kgs","ch":"1","v":"49","i":4,"w":"πάντες","lemma":"πᾶς","morph":"A.NPM"},{"book":"1Kgs","ch":"5","v":"14","i":2,"w":"πάντες","lemma":"πᾶς","morph":"A.NPM"},{"book":"1Kgs","ch":"8","v":"43","i":22,"w":"πάντες","lemma":"πᾶς","morph":"A.NPM"},{"book":"1Kgs","ch":"8","v":"60","i":2,"w":"πάντες","lemma":"πᾶς","morph":"A.NPM"},{"book":"1Kgs","ch":"8","v":"62","i":4,"w":"πάντες","lemma":"πᾶς","morph":"A.NPM"},{"book":"1Kgs","ch":"8","v":"63","i":31,"w":"πάντες","lemma":"πᾶς","morph":"A.NPM"},{"book":"1Kgs","ch":"10","v":"13","i":33,"w":"πάντες","lemma":"πᾶς","morph":"A.NPM"},{"book":"1Kgs","ch":"10","v":"24","i":1,"w":"πάντες","lemma":"πᾶς","morph":"A.NPM"},{"book":"1Kgs","ch":"11","v":"17","i":5,"w":"πάντες","lemma":"πᾶς","morph":"A.NPM"},{"book":"1Kgs","ch":"21","v":"12","i":12,"w":"πάντες","lemma":"πᾶς","morph":"A.NPM"},{"book":"1Kgs","ch":"22","v":"10","i":20,"w":"πάντες","lemma":"πᾶς","morph":"A.NPM"},{"book":"1Kgs","ch":"22","v":"12","i":1,"w":"πάντες","lemma":"πᾶς","morph":"A.NPM"},{"book":"1Kgs","ch":"22","v":"13","i":14,"w":"πάντες","lemma":"πᾶς","morph":"A.NPM"}],"παντα":[{"book":"1Kgs","ch":"2","v":"3","i":34,"w":"πάντα","lemma":"πᾶς","morph":"A.APN"},{"book":"1Kgs","ch":"4","v":"7","i":6,"w":"πάντα","lemma":"πᾶς","morph":"A.ASM"},{"book":"1Kgs","ch":"5","v":"1","i":9,"w":"πάντα","lemma":"πᾶς","morph":"A.NPN"},{"book":"1Kgs","ch":"5","v":"20","i":27,"w":"πάντα","lemma":"πᾶς","morph":"A.APN"},{"book":"1Kgs","ch":"6","v":"1d","i":15,"w":"πάντα","lemma":"πᾶς","morph":"A.ASM"},{"book":"1Kgs","ch":"7","v":"2","i":39,"w":"πάντα","lemma":"πᾶς","morph":"A.APN"},{"book":"1Kgs","ch":"7","v":"13","i":26,"w":"πάντα","lemma":"πᾶς","morph":"A.APN"},{"book":"1Kgs","ch":"7","v":"19","i":20,"w":"πάντα","lemma":"πᾶς","morph":"A.NPN"},{"book":"1Kgs","ch":"7","v":"26","i":15,"w":"πάντα","lemma":"πᾶς","morph":"A.ASM"},{"book":"1Kgs","ch":"7","v":"31","i":10,"w":"πάντα","lemma":"πᾶς","morph":"A.APN"},{"book":"1Kgs","ch":"7","v":"31","i":36,"w":"πάντα","lemma":"πᾶς","morph":"A.APN"},{"book":"1Kgs","ch":"7","v":"32","i":7,"w":"πάντα","lemma":"πᾶς","morph":"A.APN"},{"book":"1Kgs","ch":"7","v":"37","i":20,"w":"πάντα","lemma":"πᾶς","morph":"A.APN"},{"book":"1Kgs","ch":"7","v":"42","i":1,"w":"πάντα","lemma":"πᾶς","morph":"A.APN"},{"book":"1Kgs","ch":"7","v":"46","i":0,"w":"πάντα","lemma":"πᾶς","morph":"A.APN"},{"book":"1Kgs","ch":"8","v":"4","i":6,"w":"πάντα","lemma":"πᾶς","morph":"A.APN"},{"book":"1Kgs","ch":"8","v":"14","i":11,"w":"πάντα","lemma":"πᾶς","morph":"A.ASM"},{"book":"1Kgs","ch":"8","v":"43","i":13,"w":"πάντα","lemma":"πᾶς","morph":"A.APN"},{"book":"1Kgs","ch":"8","v":"50","i":11,"w":"πάντα","lemma":"πᾶς","morph":"A.APN"},{"book":"1Kgs","ch":"8","v":"56","i":11,"w":"πάντα","lemma":"πᾶς","morph":"A.APN"},{"book":"1Kgs","ch":"9","v":"4","i":22,"w":"πάντα","lemma":"πᾶς","morph":"A.APN"},{"book":"1Kgs","ch":"10","v":"2","i":26,"w":"πάντα","lemma":"πᾶς","morph":"A.APN"},{"book":"1Kgs","ch":"10","v":"13","i":8,"w":"πάντα","lemma":"πᾶς","morph":"A.APN"},{"book":"1Kgs","ch":"10","v":"21","i":1,"w":"πάντα","lemma":"πᾶς","morph":"A.APN"},{"book":"1Kgs","ch":"10","v":"21","i":11,"w":"πάντα","lemma":"πᾶς","morph":"A.APN"},{"book":"1Kgs","ch":"10","v":"22b","i":0,"w":"πάντα","lemma":"πᾶς","morph":"A.ASM"},{"book":"1Kgs","ch":"11","v":"38","i":4,"w":"πάντα","lemma":"πᾶς","morph":"A.ASM"},{"book":"1Kgs","ch":"11","v":"41","i":7,"w":"πάντα","lemma":"πᾶς","morph":"A.APN"},{"book":"1Kgs","ch":"12","v":"23","i":9,"w":"πάντα","lemma":"πᾶς","morph":"A.ASM"},{"book":"1Kgs","ch":"12","v":"24x","i":8,"w":"πάντα","lemma":"πᾶς","morph":"A.ASM"},{"book":"1Kgs","ch":"12","v":"24y","i":17,"w":"πάντα","lemma":"πᾶς","morph":"A.ASM"},{"book":"1Kgs","ch":"14","v":"23","i":9,"w":"πάντα","lemma":"πᾶς","morph":"A.ASM"},{"book":"1Kgs","ch":"14","v":"26","i":34,"w":"πάντα","lemma":"πᾶς","morph":"A.APN"},{"book":"1Kgs","ch":"14","v":"29","i":7,"w":"πάντα","lemma":"πᾶς","morph":"A.APN"},{"book":"1Kgs","ch":"15","v":"7","i":7,"w":"πάντα","lemma":"πᾶς","morph":"A.APN"},{"book":"1Kgs","ch":"15","v":"12","i":9,"w":"πάντα","lemma":"πᾶς","morph":"A.APN"},{"book":"1Kgs","ch":"15","v":"31","i":7,"w":"πάντα","lemma":"πᾶς","morph":"A.APN"},{"book":"1Kgs","ch":"16","v":"5","i":7,"w":"πάντα","lemma":"πᾶς","morph":"A.APN"},{"book":"1Kgs","ch":"16","v":"14","i":7,"w":"πάντα","lemma":"πᾶς","morph":"A.APN"},{"book":"1Kgs","ch":"16","v":"27","i":7,"w":"πάντα","lemma":"πᾶς","morph":"A.APN"},{"book":"1Kgs","ch":"18","v":"19","i":6,"w":"πάντα","lemma":"πᾶς","morph":"A.ASM"},{"book":"1Kgs","ch":"18","v":"20","i":4,"w":"πάντα","lemma":"πᾶς","morph":"A.ASM"},{"book":"1Kgs","ch":"19","v":"1","i":7,"w":"πάντα","lemma":"πᾶς","morph":"A.APN"},{"book":"1Kgs","ch":"19","v":"18","i":7,"w":"πάντα","lemma":"πᾶς","morph":"A.APN"},{"book":"1Kgs","ch":"20","v":"26","i":8,"w":"πάντα","lemma":"πᾶς","morph":"A.APN"},{"book":"1Kgs","ch":"21","v":"4","i":15,"w":"πάντα","lemma":"πᾶς","morph":"A.NPN"},{"book":"1Kgs","ch":"21","v":"9","i":10,"w":"πάντα","lemma":"πᾶς","morph":"A.APN"},{"book":"1Kgs","ch":"21","v":"13","i":15,"w":"πάντα","lemma":"πᾶς","morph":"A.ASM"},{"book":"1Kgs","ch":"22","v":"17","i":6,"w":"πάντα","lemma":"πᾶς","morph":"A.ASM"},{"book":"1Kgs","ch":"22","v":"39","i":7,"w":"πάντα","lemma":"πᾶς","morph":"A.APN"},{"book":"1Kgs","ch":"22","v":"54","i":14,"w":"πάντα","lemma":"πᾶς","morph":"A.APN"}],"παρεμβολασ":[{"book":"1Kgs","ch":"2","v":"8","i":23,"w":"παρεμβολάς","lemma":"παρεμβολή","morph":"N.APF"},{"book":"1Kgs","ch":"2","v":"35m","i":10,"w":"παρεμβολάς","lemma":"παρεμβολή","morph":"N.APF"}],"πατροσ":[{"book":"1Kgs","ch":"2","v":"12","i":8,"w":"πατρὸς","lemma":"πατήρ","morph":"N.GSM"},{"book":"1Kgs","ch":"2","v":"24","i":15,"w":"πατρός","lemma":"πατήρ","morph":"N.GSM"},{"book":"1Kgs","ch":"2","v":"26","i":37,"w":"πατρός","lemma":"πατήρ","morph":"N.GSM"},{"book":"1Kgs","ch":"2","v":"31","i":33,"w":"πατρός","lemma":"πατήρ","morph":"N.GSM"},{"book":"1Kgs","ch":"3","v":"3","i":11,"w":"πατρὸς","lemma":"πατήρ","morph":"N.GSM"},{"book":"1Kgs","ch":"3","v":"6","i":11,"w":"πατρός","lemma":"πατήρ","morph":"N.GSM"},{"book":"1Kgs","ch":"3","v":"7","i":14,"w":"πατρός","lemma":"πατήρ","morph":"N.GSM"},{"book":"1Kgs","ch":"5","v":"15","i":14,"w":"πατρὸς","lemma":"πατήρ","morph":"N.GSM"},{"book":"1Kgs","ch":"7","v":"37","i":17,"w":"πατρὸς","lemma":"πατήρ","morph":"N.GSM"},{"book":"1Kgs","ch":"8","v":"15","i":17,"w":"πατρός","lemma":"πατήρ","morph":"N.GSM"},{"book":"1Kgs","ch":"8","v":"17","i":7,"w":"πατρός","lemma":"πατήρ","morph":"N.GSM"},{"book":"1Kgs","ch":"8","v":"20","i":13,"w":"πατρός","lemma":"πατήρ","morph":"N.GSM"},{"book":"1Kgs","ch":"11","v":"4","i":22,"w":"πατρὸς","lemma":"πατήρ","morph":"N.GSM"},{"book":"1Kgs","ch":"11","v":"17","i":11,"w":"πατρὸς","lemma":"πατήρ","morph":"N.GSM"},{"book":"1Kgs","ch":"11","v":"27","i":20,"w":"πατρὸς","lemma":"πατήρ","morph":"N.GSM"},{"book":"1Kgs","ch":"11","v":"43","i":14,"w":"πατρὸς","lemma":"πατήρ","morph":"N.GSM"},{"book":"1Kgs","ch":"12","v":"4","i":15,"w":"πατρός","lemma":"πατήρ","morph":"N.GSM"},{"book":"1Kgs","ch":"12","v":"6","i":12,"w":"πατρὸς","lemma":"πατήρ","morph":"N.GSM"},{"book":"1Kgs","ch":"12","v":"10","i":50,"w":"πατρός","lemma":"πατήρ","morph":"N.GSM"},{"book":"1Kgs","ch":"12","v":"24a","i":67,"w":"πατρὸς","lemma":"πατήρ","morph":"N.GSM"},{"book":"1Kgs","ch":"12","v":"24r","i":50,"w":"πατρός","lemma":"πατήρ","morph":"N.GSM"},{"book":"1Kgs","ch":"13","v":"11","i":42,"w":"πατρὸς","lemma":"πατήρ","morph":"N.GSM"},{"book":"1Kgs","ch":"15","v":"3","i":6,"w":"πατρὸς","lemma":"πατήρ","morph":"N.GSM"},{"book":"1Kgs","ch":"15","v":"3","i":28,"w":"πατρὸς","lemma":"πατήρ","morph":"N.GSM"},{"book":"1Kgs","ch":"15","v":"15","i":5,"w":"πατρὸς","lemma":"πατήρ","morph":"N.GSM"},{"book":"1Kgs","ch":"15","v":"19","i":13,"w":"πατρός","lemma":"πατήρ","morph":"N.GSM"},{"book":"1Kgs","ch":"15","v":"19","i":17,"w":"πατρός","lemma":"πατήρ","morph":"N.GSM"},{"book":"1Kgs","ch":"15","v":"26","i":11,"w":"πατρὸς","lemma":"πατήρ","morph":"N.GSM"},{"book":"1Kgs","ch":"16","v":"28b","i":7,"w":"πατρὸς","lemma":"πατήρ","morph":"N.GSM"},{"book":"1Kgs","ch":"16","v":"28d","i":12,"w":"πατρὸς","lemma":"πατήρ","morph":"N.GSM"},{"book":"1Kgs","ch":"18","v":"18","i":15,"w":"πατρός","lemma":"πατήρ","morph":"N.GSM"},{"book":"1Kgs","ch":"21","v":"34","i":13,"w":"πατρός","lemma":"πατήρ","morph":"N.GSM"},{"book":"1Kgs","ch":"22","v":"43","i":7,"w":"πατρὸς","lemma":"πατήρ","morph":"N.GSM"},{"book":"1Kgs","ch":"22","v":"51","i":17,"w":"πατρὸς","lemma":"πατήρ","morph":"N.GSM"},{"book":"1Kgs","ch":"22","v":"53","i":12,"w":"πατρὸς","lemma":"πατήρ","morph":"N.GSM"}],"παρα":[{"book":"1Kgs","ch":"2","v":"15","i":31,"w":"παρὰ","lemma":"παρά","morph":"P"},{"book":"1Kgs","ch":"2","v":"16","i":6,"w":"παρὰ","lemma":"παρά","morph":"P"},{"book":"1Kgs","ch":"2","v":"20","i":8,"w":"παρὰ","lemma":"παρά","morph":"P"},{"book":"1Kgs","ch":"2","v":"33","i":36,"w":"παρὰ","lemma":"παρά","morph":"P"},{"book":"1Kgs","ch":"2","v":"35a","i":17,"w":"παρὰ","lemma":"παρά","morph":"P"},{"book":"1Kgs","ch":"4","v":"12","i":12,"w":"παρὰ","lemma":"παρά","morph":"P"},{"book":"1Kgs","ch":"5","v":"9","i":17,"w":"παρὰ","lemma":"παρά","morph":"P"},{"book":"1Kgs","ch":"5","v":"14","i":12,"w":"παρὰ","lemma":"παρά","morph":"P"},{"book":"1Kgs","ch":"10","v":"3","i":12,"w":"παρὰ","lemma":"παρά","morph":"P"},{"book":"1Kgs","ch":"10","v":"19","i":27,"w":"παρὰ","lemma":"παρά","morph":"P"},{"book":"1Kgs","ch":"12","v":"15","i":10,"w":"παρὰ","lemma":"παρά","morph":"P"},{"book":"1Kgs","ch":"13","v":"24","i":31,"w":"παρὰ","lemma":"παρά","morph":"P"},{"book":"1Kgs","ch":"13","v":"28","i":18,"w":"παρὰ","lemma":"παρά","morph":"P"},{"book":"1Kgs","ch":"13","v":"31","i":28,"w":"παρὰ","lemma":"παρά","morph":"P"},{"book":"1Kgs","ch":"16","v":"24","i":7,"w":"παρὰ","lemma":"παρά","morph":"P"},{"book":"1Kgs","ch":"18","v":"38","i":3,"w":"παρὰ","lemma":"παρά","morph":"P"},{"book":"1Kgs","ch":"20","v":"1","i":8,"w":"παρὰ","lemma":"παρά","morph":"P"},{"book":"1Kgs","ch":"20","v":"3","i":8,"w":"παρὰ","lemma":"παρά","morph":"P"},{"book":"1Kgs","ch":"21","v":"34","i":11,"w":"παρὰ","lemma":"παρά","morph":"P"},{"book":"1Kgs","ch":"22","v":"51","i":9,"w":"παρὰ","lemma":"παρά","morph":"P"}],"πασαν":[{"book":"1Kgs","ch":"2","v":"44","i":8,"w":"πᾶσαν","lemma":"πᾶς","morph":"A.ASF"},{"book":"1Kgs","ch":"6","v":"1d","i":20,"w":"πᾶσαν","lemma":"πᾶς","morph":"A.ASF"},{"book":"1Kgs","ch":"8","v":"38","i":0,"w":"πᾶσαν","lemma":"πᾶς","morph":"A.ASF"},{"book":"1Kgs","ch":"8","v":"38","i":2,"w":"πᾶσαν","lemma":"πᾶς","morph":"A.ASF"},{"book":"1Kgs","ch":"8","v":"55","i":4,"w":"πᾶσαν","lemma":"πᾶς","morph":"A.ASF"},{"book":"1Kgs","ch":"9","v":"1","i":15,"w":"πᾶσαν","lemma":"πᾶς","morph":"A.ASF"},{"book":"1Kgs","ch":"9","v":"3","i":22,"w":"πᾶσαν","lemma":"πᾶς","morph":"A.ASF"},{"book":"1Kgs","ch":"10","v":"4","i":4,"w":"πᾶσαν","lemma":"πᾶς","morph":"A.ASF"},{"book":"1Kgs","ch":"10","v":"7","i":28,"w":"πᾶσαν","lemma":"πᾶς","morph":"A.ASF"},{"book":"1Kgs","ch":"10","v":"8","i":17,"w":"πᾶσαν","lemma":"πᾶς","morph":"A.ASF"},{"book":"1Kgs","ch":"11","v":"41","i":11,"w":"πᾶσαν","lemma":"πᾶς","morph":"A.ASF"},{"book":"1Kgs","ch":"15","v":"20","i":30,"w":"πᾶσαν","lemma":"πᾶς","morph":"A.ASF"},{"book":"1Kgs","ch":"15","v":"29","i":12,"w":"πᾶσαν","lemma":"πᾶς","morph":"A.ASF"},{"book":"1Kgs","ch":"16","v":"7","i":15,"w":"πᾶσαν","lemma":"πᾶς","morph":"A.ASF"},{"book":"1Kgs","ch":"21","v":"1","i":4,"w":"πᾶσαν","lemma":"πᾶς","morph":"A.ASF"}],"πατρι":[{"book":"1Kgs","ch":"2","v":"44","i":22,"w":"πατρί","lemma":"πατήρ","morph":"N.DSM"},{"book":"1Kgs","ch":"8","v":"24","i":7,"w":"πατρί","lemma":"πατήρ","morph":"N.DSM"},{"book":"1Kgs","ch":"8","v":"25","i":13,"w":"πατρί","lemma":"πατήρ","morph":"N.DSM"},{"book":"1Kgs","ch":"8","v":"26","i":14,"w":"πατρί","lemma":"πατήρ","morph":"N.DSM"},{"book":"1Kgs","ch":"9","v":"5","i":16,"w":"πατρί","lemma":"πατήρ","morph":"N.DSM"}],"παντων":[{"book":"1Kgs","ch":"2","v":"35b","i":9,"w":"πάντων","lemma":"πᾶς","morph":"A.GPM"},{"book":"1Kgs","ch":"2","v":"46g","i":5,"w":"πάντων","lemma":"πᾶς","morph":"A.GPN"},{"book":"1Kgs","ch":"5","v":"4","i":11,"w":"πάντων","lemma":"πᾶς","morph":"A.GPN"},{"book":"1Kgs","ch":"5","v":"10","i":7,"w":"πάντων","lemma":"πᾶς","morph":"A.GPM"},{"book":"1Kgs","ch":"5","v":"14","i":13,"w":"πάντων","lemma":"πᾶς","morph":"A.GPM"},{"book":"1Kgs","ch":"5","v":"22","i":7,"w":"πάντων","lemma":"πᾶς","morph":"A.GPM"},{"book":"1Kgs","ch":"8","v":"39","i":34,"w":"πάντων","lemma":"πᾶς","morph":"A.GPM"},{"book":"1Kgs","ch":"8","v":"53","i":8,"w":"πάντων","lemma":"πᾶς","morph":"A.GPM"},{"book":"1Kgs","ch":"10","v":"13","i":14,"w":"πάντων","lemma":"πᾶς","morph":"A.GPM"},{"book":"1Kgs","ch":"10","v":"15","i":9,"w":"πάντων","lemma":"πᾶς","morph":"A.GPM"},{"book":"1Kgs","ch":"10","v":"26a","i":3,"w":"πάντων","lemma":"πᾶς","morph":"A.GPM"},{"book":"1Kgs","ch":"14","v":"24","i":9,"w":"πάντων","lemma":"πᾶς","morph":"A.GPN"},{"book":"1Kgs","ch":"15","v":"5","i":10,"w":"πάντων","lemma":"πᾶς","morph":"A.GPM"},{"book":"1Kgs","ch":"22","v":"22","i":9,"w":"πάντων","lemma":"πᾶς","morph":"A.GPM"},{"book":"1Kgs","ch":"22","v":"23","i":9,"w":"πάντων","lemma":"πᾶς","morph":"A.GPM"}],"πασαισ":[{"book":"1Kgs","ch":"2","v":"46b","i":5,"w":"πάσαις","lemma":"πᾶς","morph":"A.DPF"},{"book":"1Kgs","ch":"7","v":"23","i":12,"w":"πάσαις","lemma":"πᾶς","morph":"A.DPF"},{"book":"1Kgs","ch":"8","v":"58","i":8,"w":"πάσαις","lemma":"πᾶς","morph":"A.DPF"},{"book":"1Kgs","ch":"11","v":"7","i":3,"w":"πάσαις","lemma":"πᾶς","morph":"A.DPF"}],"πασασ":[{"book":"1Kgs","ch":"2","v":"46b","i":16,"w":"πάσας","lemma":"πᾶς","morph":"A.APF"},{"book":"1Kgs","ch":"2","v":"46g","i":34,"w":"πάσας","lemma":"πᾶς","morph":"A.APF"},{"book":"1Kgs","ch":"5","v":"15","i":22,"w":"πάσας","lemma":"πᾶς","morph":"A.APF"},{"book":"1Kgs","ch":"7","v":"23","i":3,"w":"πάσας","lemma":"πᾶς","morph":"A.APF"},{"book":"1Kgs","ch":"8","v":"40","i":3,"w":"πάσας","lemma":"πᾶς","morph":"A.APF"},{"book":"1Kgs","ch":"8","v":"58","i":13,"w":"πάσας","lemma":"πᾶς","morph":"A.APF"},{"book":"1Kgs","ch":"9","v":"3","i":51,"w":"πάσας","lemma":"πᾶς","morph":"A.APF"},{"book":"1Kgs","ch":"10","v":"22a","i":52,"w":"πάσας","lemma":"πᾶς","morph":"A.APF"},{"book":"1Kgs","ch":"10","v":"22a","i":58,"w":"πάσας","lemma":"πᾶς","morph":"A.APF"},{"book":"1Kgs","ch":"11","v":"14","i":41,"w":"πάσας","lemma":"πᾶς","morph":"A.APF"},{"book":"1Kgs","ch":"11","v":"34","i":14,"w":"πάσας","lemma":"πᾶς","morph":"A.APF"},{"book":"1Kgs","ch":"11","v":"36","i":15,"w":"πάσας","lemma":"πᾶς","morph":"A.APF"},{"book":"1Kgs","ch":"12","v":"7","i":27,"w":"πάσας","lemma":"πᾶς","morph":"A.APF"},{"book":"1Kgs","ch":"14","v":"30","i":10,"w":"πάσας","lemma":"πᾶς","morph":"A.APF"},{"book":"1Kgs","ch":"15","v":"5","i":14,"w":"πάσας","lemma":"πᾶς","morph":"A.APF"},{"book":"1Kgs","ch":"15","v":"14","i":13,"w":"πάσας","lemma":"πᾶς","morph":"A.APF"},{"book":"1Kgs","ch":"15","v":"16","i":12,"w":"πάσας","lemma":"πᾶς","morph":"A.APF"},{"book":"1Kgs","ch":"22","v":"39","i":16,"w":"πάσας","lemma":"πᾶς","morph":"A.APF"}],"παντι":[{"book":"1Kgs","ch":"2","v":"46f","i":4,"w":"παντὶ","lemma":"πᾶς","morph":"A.DSM"},{"book":"1Kgs","ch":"8","v":"38","i":6,"w":"παντὶ","lemma":"πᾶς","morph":"A.DSM"},{"book":"1Kgs","ch":"9","v":"11","i":18,"w":"παντὶ","lemma":"πᾶς","morph":"A.DSN"},{"book":"1Kgs","ch":"15","v":"22","i":5,"w":"παντὶ","lemma":"πᾶς","morph":"A.DSM"},{"book":"1Kgs","ch":"20","v":"19","i":19,"w":"παντὶ","lemma":"πᾶς","morph":"A.DSM"},{"book":"1Kgs","ch":"21","v":"10","i":22,"w":"παντὶ","lemma":"πᾶς","morph":"A.DSM"}],"πασιν":[{"book":"1Kgs","ch":"2","v":"46f","i":13,"w":"πᾶσιν","lemma":"πᾶς","morph":"A.DPM"},{"book":"1Kgs","ch":"2","v":"46k","i":4,"w":"πᾶσιν","lemma":"πᾶς","morph":"A.DPM"},{"book":"1Kgs","ch":"3","v":"15","i":38,"w":"πᾶσιν","lemma":"πᾶς","morph":"A.DPM"},{"book":"1Kgs","ch":"8","v":"52","i":27,"w":"πᾶσιν","lemma":"πᾶς","morph":"A.DPN"},{"book":"1Kgs","ch":"8","v":"56","i":19,"w":"πᾶσιν","lemma":"πᾶς","morph":"A.DPM"},{"book":"1Kgs","ch":"10","v":"29","i":17,"w":"πᾶσιν","lemma":"πᾶς","morph":"A.DPM"},{"book":"1Kgs","ch":"14","v":"22","i":11,"w":"πᾶσιν","lemma":"πᾶς","morph":"A.DPM"}],"παιδαριον":[{"book":"1Kgs","ch":"3","v":"7","i":19,"w":"παιδάριον","lemma":"παιδάριον","morph":"N.ASN"},{"book":"1Kgs","ch":"11","v":"17","i":21,"w":"παιδάριον","lemma":"παιδάριον","morph":"N.NSN"},{"book":"1Kgs","ch":"11","v":"28","i":10,"w":"παιδάριον","lemma":"παιδάριον","morph":"N.ASN"},{"book":"1Kgs","ch":"12","v":"24g","i":3,"w":"παιδάριον","lemma":"παιδάριον","morph":"N.NSN"},{"book":"1Kgs","ch":"12","v":"24l","i":52,"w":"παιδάριον","lemma":"παιδάριον","morph":"N.NSN"},{"book":"1Kgs","ch":"12","v":"24m","i":37,"w":"παιδάριον","lemma":"παιδάριον","morph":"N.ASN"},{"book":"1Kgs","ch":"12","v":"24n","i":15,"w":"παιδάριον","lemma":"παιδάριον","morph":"N.NSN"},{"book":"1Kgs","ch":"17","v":"22","i":6,"w":"παιδάριον","lemma":"παιδάριον","morph":"N.NSN"},{"book":"1Kgs","ch":"18","v":"43","i":14,"w":"παιδάριον","lemma":"παιδάριον","morph":"N.NSN"},{"book":"1Kgs","ch":"18","v":"43","i":30,"w":"παιδάριον","lemma":"παιδάριον","morph":"N.NSN"},{"book":"1Kgs","ch":"19","v":"3","i":20,"w":"παιδάριον","lemma":"παιδάριον","morph":"N.NSN"}],"παρ᾿":[{"book":"1Kgs","ch":"3","v":"11","i":8,"w":"παρ᾿","lemma":"παρά","morph":"P"},{"book":"1Kgs","ch":"12","v":"24","i":20,"w":"παρ᾿","lemma":"παρά","morph":"P"},{"book":"1Kgs","ch":"12","v":"24y","i":49,"w":"παρ᾿","lemma":"παρά","morph":"P"},{"book":"1Kgs","ch":"13","v":"24","i":25,"w":"παρ᾿","lemma":"παρά","morph":"P"},{"book":"1Kgs","ch":"21","v":"20","i":3,"w":"παρ᾿","lemma":"παρά","morph":"P"},{"book":"1Kgs","ch":"21","v":"20","i":9,"w":"παρ᾿","lemma":"παρά","morph":"P"},{"book":"1Kgs","ch":"21","v":"40","i":24,"w":"παρ᾿","lemma":"παρά","morph":"P"}],"παραγινεται":[{"book":"1Kgs","ch":"3","v":"15","i":9,"w":"παραγίνεται","lemma":"παραγίνομαι","morph":"V.PMI3S"}],"παισιν":[{"book":"1Kgs","ch":"3","v":"15","i":40,"w":"παισὶν","lemma":"παῖς","morph":"N.DPM"},{"book":"1Kgs","ch":"21","v":"12","i":22,"w":"παισὶν","lemma":"παῖς","morph":"N.DPM"},{"book":"1Kgs","ch":"21","v":"31","i":3,"w":"παισὶν","lemma":"παῖς","morph":"N.DPM"}],"παρεξ":[{"book":"1Kgs","ch":"3","v":"18","i":26,"w":"πάρεξ","lemma":"παρέξ","morph":"P"},{"book":"1Kgs","ch":"12","v":"20","i":30,"w":"πάρεξ","lemma":"παρέξ","morph":"P"}],"παιδιον":[{"book":"1Kgs","ch":"3","v":"25","i":6,"w":"παιδίον","lemma":"παιδίον","morph":"N.ASN"},{"book":"1Kgs","ch":"3","v":"26","i":32,"w":"παιδίον","lemma":"παιδίον","morph":"N.ASN"},{"book":"1Kgs","ch":"3","v":"27","i":8,"w":"παιδίον","lemma":"παιδίον","morph":"N.ASN"}],"πατριασ":[{"book":"1Kgs","ch":"4","v":"6","i":9,"w":"πατριᾶς","lemma":"πατριά","morph":"N.GSF"}],"παραλλασσουσιν":[{"book":"1Kgs","ch":"5","v":"1","i":21,"w":"παραλλάσσουσιν","lemma":"παραλλάσσω","morph":"V.PAI3P"}],"παραβολασ":[{"book":"1Kgs","ch":"5","v":"12","i":4,"w":"παραβολάς","lemma":"παραβολή","morph":"N.APF"}],"παρεγινοντο":[{"book":"1Kgs","ch":"5","v":"14","i":1,"w":"παρεγίνοντο","lemma":"παραγίνομαι","morph":"V.IMI3P"}],"πατερα":[{"book":"1Kgs","ch":"5","v":"17","i":4,"w":"πατέρα","lemma":"πατήρ","morph":"N.ASM"},{"book":"1Kgs","ch":"5","v":"19","i":19,"w":"πατέρα","lemma":"πατήρ","morph":"N.ASM"},{"book":"1Kgs","ch":"8","v":"18","i":6,"w":"πατέρα","lemma":"πατήρ","morph":"N.ASM"},{"book":"1Kgs","ch":"11","v":"12","i":11,"w":"πατέρα","lemma":"πατήρ","morph":"N.ASM"},{"book":"1Kgs","ch":"19","v":"20","i":13,"w":"πατέρα","lemma":"πατήρ","morph":"N.ASM"}],"παν":[{"book":"1Kgs","ch":"5","v":"22","i":14,"w":"πᾶν","lemma":"πᾶς","morph":"A.ASN"},{"book":"1Kgs","ch":"5","v":"24","i":8,"w":"πᾶν","lemma":"πᾶς","morph":"A.ASN"},{"book":"1Kgs","ch":"6","v":"7","i":16,"w":"πᾶν","lemma":"πᾶς","morph":"A.NSN"},{"book":"1Kgs","ch":"7","v":"2","i":27,"w":"πᾶν","lemma":"πᾶς","morph":"A.ASN"},{"book":"1Kgs","ch":"7","v":"37","i":2,"w":"πᾶν","lemma":"πᾶς","morph":"A.ASN"},{"book":"1Kgs","ch":"8","v":"37","i":24,"w":"πᾶν","lemma":"πᾶς","morph":"A.ASN"},{"book":"1Kgs","ch":"8","v":"37","i":26,"w":"πᾶν","lemma":"πᾶς","morph":"A.ASN"},{"book":"1Kgs","ch":"11","v":"15","i":19,"w":"πᾶν","lemma":"πᾶς","morph":"A.NSN"},{"book":"1Kgs","ch":"11","v":"16","i":15,"w":"πᾶν","lemma":"πᾶς","morph":"A.ASN"},{"book":"1Kgs","ch":"12","v":"24f","i":27,"w":"πᾶν","lemma":"πᾶς","morph":"A.NSN"},{"book":"1Kgs","ch":"12","v":"24u","i":33,"w":"πᾶν","lemma":"πᾶς","morph":"A.NSN"},{"book":"1Kgs","ch":"12","v":"24u","i":37,"w":"πᾶν","lemma":"πᾶς","morph":"A.NSN"},{"book":"1Kgs","ch":"15","v":"22","i":29,"w":"πᾶν","lemma":"πᾶς","morph":"A.ASN"},{"book":"1Kgs","ch":"19","v":"18","i":16,"w":"πᾶν","lemma":"πᾶς","morph":"A.ASN"},{"book":"1Kgs","ch":"21","v":"15","i":20,"w":"πᾶν","lemma":"πᾶς","morph":"A.NSN"}],"παρακυπτομενασ":[{"book":"1Kgs","ch":"6","v":"4","i":5,"w":"παρακυπτομένας","lemma":"παρακύπτω","morph":"V.PMPAPF"}],"παχοσ":[{"book":"1Kgs","ch":"7","v":"3","i":24,"w":"πάχος","lemma":"πάχος","morph":"N.NSN"},{"book":"1Kgs","ch":"7","v":"12","i":12,"w":"πάχος","lemma":"πάχος","morph":"N.NSN"},{"book":"1Kgs","ch":"7","v":"43","i":20,"w":"πάχος","lemma":"πάχος","morph":"N.NSN"}],"παχει":[{"book":"1Kgs","ch":"7","v":"9","i":14,"w":"πάχει","lemma":"πάχος","morph":"N.DSN"},{"book":"1Kgs","ch":"7","v":"33","i":11,"w":"πάχει","lemma":"πάχος","morph":"N.DSN"}],"παλαιστησ":[{"book":"1Kgs","ch":"7","v":"12","i":14,"w":"παλαιστής","lemma":"παλαιστή","morph":"N.GSF"}],"πασα":[{"book":"1Kgs","ch":"8","v":"14","i":14,"w":"πᾶσα","lemma":"πᾶς","morph":"A.NSF"},{"book":"1Kgs","ch":"15","v":"23","i":7,"w":"πᾶσα","lemma":"πᾶς","morph":"A.NSF"},{"book":"1Kgs","ch":"16","v":"28c","i":5,"w":"πᾶσα","lemma":"πᾶς","morph":"A.NSF"},{"book":"1Kgs","ch":"22","v":"19","i":22,"w":"πᾶσα","lemma":"πᾶς","morph":"A.NSF"}],"πατρασιν":[{"book":"1Kgs","ch":"8","v":"34","i":24,"w":"πατράσιν","lemma":"πατήρ","morph":"N.DPM"},{"book":"1Kgs","ch":"8","v":"40","i":15,"w":"πατράσιν","lemma":"πατήρ","morph":"N.DPM"},{"book":"1Kgs","ch":"8","v":"48","i":31,"w":"πατράσιν","lemma":"πατήρ","morph":"N.DPM"},{"book":"1Kgs","ch":"8","v":"58","i":23,"w":"πατράσιν","lemma":"πατήρ","morph":"N.DPM"},{"book":"1Kgs","ch":"22","v":"51","i":11,"w":"πατράσιν","lemma":"πατήρ","morph":"N.DPM"}],"παραδωσεισ":[{"book":"1Kgs","ch":"8","v":"46","i":15,"w":"παραδώσεις","lemma":"παραδίδωμι","morph":"V.FAI2S"}],"πατερασ":[{"book":"1Kgs","ch":"8","v":"53","i":25,"w":"πατέρας","lemma":"πατήρ","morph":"N.APM"},{"book":"1Kgs","ch":"9","v":"9","i":11,"w":"πατέρας","lemma":"πατήρ","morph":"N.APM"},{"book":"1Kgs","ch":"19","v":"4","i":40,"w":"πατέρας","lemma":"πατήρ","morph":"N.APM"}],"παιδων":[{"book":"1Kgs","ch":"9","v":"27","i":7,"w":"παίδων","lemma":"παῖς","morph":"N.GPM"},{"book":"1Kgs","ch":"9","v":"27","i":16,"w":"παίδων","lemma":"παῖς","morph":"N.GPM"},{"book":"1Kgs","ch":"10","v":"5","i":7,"w":"παίδων","lemma":"παῖς","morph":"N.GPM"},{"book":"1Kgs","ch":"11","v":"17","i":9,"w":"παίδων","lemma":"παῖς","morph":"N.GPM"},{"book":"1Kgs","ch":"14","v":"26","i":24,"w":"παίδων","lemma":"παῖς","morph":"N.GPM"},{"book":"1Kgs","ch":"15","v":"18","i":22,"w":"παίδων","lemma":"παῖς","morph":"N.GPM"},{"book":"1Kgs","ch":"21","v":"6","i":20,"w":"παίδων","lemma":"παῖς","morph":"N.GPM"}],"παρεωραμενοσ":[{"book":"1Kgs","ch":"10","v":"3","i":11,"w":"παρεωραμένος","lemma":"παρεῖδον","morph":"V.XMPNSM"}],"παρεγενομην":[{"book":"1Kgs","ch":"10","v":"7","i":8,"w":"παρεγενόμην","lemma":"παραγίνομαι","morph":"V.AMI1S"}],"παρεστηκοτεσ":[{"book":"1Kgs","ch":"10","v":"8","i":10,"w":"παρεστηκότες","lemma":"παρίστημι","morph":"V.XAPNPM"},{"book":"1Kgs","ch":"12","v":"10","i":11,"w":"παρεστηκότες","lemma":"παρίστημι","morph":"V.XAPNPM"}],"παση":[{"book":"1Kgs","ch":"10","v":"20","i":14,"w":"πάσῃ","lemma":"πᾶς","morph":"A.DSF"},{"book":"1Kgs","ch":"10","v":"22a","i":74,"w":"πάσῃ","lemma":"πᾶς","morph":"A.DSF"},{"book":"1Kgs","ch":"16","v":"26","i":3,"w":"πάσῃ","lemma":"πᾶς","morph":"A.DSF"},{"book":"1Kgs","ch":"22","v":"43","i":3,"w":"πάσῃ","lemma":"πᾶς","morph":"A.DSF"}],"παλλακαι":[{"book":"1Kgs","ch":"11","v":"1","i":12,"w":"παλλακαὶ","lemma":"παλλακή","morph":"N.NPF"}],"παραπαν":[{"book":"1Kgs","ch":"11","v":"10","i":8,"w":"παράπαν","lemma":"παράπαν","morph":"D"}],"πασων":[{"book":"1Kgs","ch":"11","v":"32","i":20,"w":"πασῶν","lemma":"πᾶς","morph":"A.GPF"},{"book":"1Kgs","ch":"14","v":"21","i":35,"w":"πασῶν","lemma":"πᾶς","morph":"A.GPF"},{"book":"1Kgs","ch":"16","v":"13","i":1,"w":"πασῶν","lemma":"πᾶς","morph":"A.GPF"}],"παρηγγειλεν":[{"book":"1Kgs","ch":"12","v":"6","i":1,"w":"παρήγγειλεν","lemma":"παραγγέλλω","morph":"V.AAI3S"},{"book":"1Kgs","ch":"15","v":"22","i":4,"w":"παρήγγειλεν","lemma":"παραγγέλλω","morph":"V.AAI3S"}],"παρεστωτεσ":[{"book":"1Kgs","ch":"12","v":"6","i":8,"w":"παρεστῶτες","lemma":"παρίστημι","morph":"V.AAPNPM"}],"παιδαριων":[{"book":"1Kgs","ch":"12","v":"8","i":13,"w":"παιδαρίων","lemma":"παιδάριον","morph":"N.GPN"},{"book":"1Kgs","ch":"12","v":"14","i":8,"w":"παιδαρίων","lemma":"παιδάριον","morph":"N.GPN"}],"παρεστηκοτων":[{"book":"1Kgs","ch":"12","v":"8","i":19,"w":"παρεστηκότων","lemma":"παρίστημι","morph":"V.XAPGPN"}],"παιδαρια":[{"book":"1Kgs","ch":"12","v":"10","i":5,"w":"παιδάρια","lemma":"παιδάριον","morph":"N.NPN"},{"book":"1Kgs","ch":"12","v":"24s","i":17,"w":"παιδάρια","lemma":"παιδάριον","morph":"N.NPN"},{"book":"1Kgs","ch":"16","v":"28g","i":13,"w":"παιδάριά","lemma":"παιδάριον","morph":"N.APN"},{"book":"1Kgs","ch":"21","v":"15","i":4,"w":"παιδάρια","lemma":"παιδάριον","morph":"N.APN"},{"book":"1Kgs","ch":"21","v":"17","i":2,"w":"παιδάρια","lemma":"παιδάριον","morph":"N.NPN"},{"book":"1Kgs","ch":"21","v":"19","i":7,"w":"παιδάρια","lemma":"παιδάριον","morph":"N.NPN"}],"παχυτερα":[{"book":"1Kgs","ch":"12","v":"10","i":46,"w":"παχυτέρα","lemma":"παχύς","morph":"A.ASFC"},{"book":"1Kgs","ch":"12","v":"24r","i":45,"w":"παχυτέρα","lemma":"παχύς","morph":"A.ASFC"}],"παιδευσω":[{"book":"1Kgs","ch":"12","v":"11","i":24,"w":"παιδεύσω","lemma":"παιδεύω","morph":"V.FAI1S"},{"book":"1Kgs","ch":"12","v":"14","i":31,"w":"παιδεύσω","lemma":"παιδεύω","morph":"V.FAI1S"}],"παρεγενοντο":[{"book":"1Kgs","ch":"12","v":"12","i":1,"w":"παρεγένοντο","lemma":"παραγίνομαι","morph":"V.AMI3P"},{"book":"1Kgs","ch":"21","v":"27","i":6,"w":"παρεγένοντο","lemma":"παραγίνομαι","morph":"V.AMI3P"}],"παρεστησεν":[{"book":"1Kgs","ch":"12","v":"32","i":38,"w":"παρέστησεν","lemma":"παρίστημι","morph":"V.AAI3S"}],"παιδαριου":[{"book":"1Kgs","ch":"12","v":"24g","i":14,"w":"παιδαρίου","lemma":"παιδάριον","morph":"N.GSN"},{"book":"1Kgs","ch":"12","v":"24g","i":30,"w":"παιδαρίου","lemma":"παιδάριον","morph":"N.GSN"},{"book":"1Kgs","ch":"17","v":"21","i":20,"w":"παιδαρίου","lemma":"παιδάριον","morph":"N.GSN"}],"παιδαριω":[{"book":"1Kgs","ch":"12","v":"24k","i":21,"w":"παιδαρίῳ","lemma":"παιδάριον","morph":"N.DSN"},{"book":"1Kgs","ch":"17","v":"21","i":3,"w":"παιδαρίῳ","lemma":"παιδάριον","morph":"N.DSN"},{"book":"1Kgs","ch":"18","v":"43","i":3,"w":"παιδαρίῳ","lemma":"παιδάριον","morph":"N.DSN"}],"παρεγενετο":[{"book":"1Kgs","ch":"13","v":"1","i":7,"w":"παρεγένετο","lemma":"παραγίνομαι","morph":"V.AMI3S"}],"παρεπικρανασ":[{"book":"1Kgs","ch":"13","v":"21","i":17,"w":"παρεπίκρανας","lemma":"παραπικραίνω","morph":"V.AAI2S"}],"παραπορευομενοι":[{"book":"1Kgs","ch":"13","v":"25","i":3,"w":"παραπορευόμενοι","lemma":"παραπορεύομαι","morph":"V.PMPNPM"}],"παρεπικρανε":[{"book":"1Kgs","ch":"13","v":"26","i":17,"w":"παρεπίκρανε","lemma":"παραπικραίνω","morph":"V.AAI3S"}],"παρεζηλωσεν":[{"book":"1Kgs","ch":"14","v":"22","i":8,"w":"παρεζήλωσεν","lemma":"παραζηλόω","morph":"V.AAI3S"}],"πατερεσ":[{"book":"1Kgs","ch":"14","v":"22","i":15,"w":"πατέρες","lemma":"πατήρ","morph":"N.NPM"},{"book":"1Kgs","ch":"15","v":"12","i":15,"w":"πατέρες","lemma":"πατήρ","morph":"N.NPM"}],"παρατρεχοντων":[{"book":"1Kgs","ch":"14","v":"27","i":16,"w":"παρατρεχόντων","lemma":"παρατρέχω","morph":"V.PAPGPM"},{"book":"1Kgs","ch":"14","v":"28","i":21,"w":"παρατρεχόντων","lemma":"παρατρέχω","morph":"V.PAPGPM"}],"παρατρεχοντεσ":[{"book":"1Kgs","ch":"14","v":"28","i":13,"w":"παρατρέχοντες","lemma":"παρατρέχω","morph":"V.PAPNPM"}],"παροργισμω":[{"book":"1Kgs","ch":"15","v":"30","i":11,"w":"παροργισμῷ","lemma":"παροργισμός","morph":"N.DSM"}],"παρωργισεν":[{"book":"1Kgs","ch":"15","v":"30","i":14,"w":"παρώργισεν","lemma":"παροργίζω","morph":"V.AAI3S"},{"book":"1Kgs","ch":"22","v":"54","i":8,"w":"παρώργισεν","lemma":"παροργίζω","morph":"V.AAI3S"}],"παροργισαι":[{"book":"1Kgs","ch":"16","v":"2","i":30,"w":"παροργίσαι","lemma":"παροργίζω","morph":"V.AAN"},{"book":"1Kgs","ch":"16","v":"7","i":23,"w":"παροργίσαι","lemma":"παροργίζω","morph":"V.AAN"},{"book":"1Kgs","ch":"16","v":"13","i":15,"w":"παροργίσαι","lemma":"παροργίζω","morph":"V.AAN"},{"book":"1Kgs","ch":"16","v":"26","i":18,"w":"παροργίσαι","lemma":"παροργίζω","morph":"V.AAN"},{"book":"1Kgs","ch":"16","v":"33","i":11,"w":"παροργίσαι","lemma":"παροργίζω","morph":"V.AAN"},{"book":"1Kgs","ch":"20","v":"20","i":22,"w":"παροργίσαι","lemma":"παροργίζω","morph":"V.AAN"}],"παταξαι":[{"book":"1Kgs","ch":"16","v":"7","i":40,"w":"πατάξαι","lemma":"πατάσσω","morph":"V.AAN"},{"book":"1Kgs","ch":"21","v":"35","i":24,"w":"πατάξαι","lemma":"πατάσσω","morph":"V.AAN"}],"παρεμβολη":[{"book":"1Kgs","ch":"16","v":"15","i":9,"w":"παρεμβολὴ","lemma":"παρεμβολή","morph":"N.NSF"},{"book":"1Kgs","ch":"16","v":"16","i":6,"w":"παρεμβολῇ","lemma":"παρεμβολή","morph":"N.DSF"},{"book":"1Kgs","ch":"16","v":"16","i":32,"w":"παρεμβολῇ","lemma":"παρεμβολή","morph":"N.DSF"}],"παροργισματα":[{"book":"1Kgs","ch":"16","v":"33","i":9,"w":"παροργίσματα","lemma":"παρόργισμα","morph":"N.APN"}],"παρεστην":[{"book":"1Kgs","ch":"17","v":"1","i":23,"w":"παρέστην","lemma":"παρίστημι","morph":"V.AAI1S"},{"book":"1Kgs","ch":"18","v":"15","i":8,"w":"παρέστην","lemma":"παρίστημι","morph":"V.AAI1S"}],"παρηλθεν":[{"book":"1Kgs","ch":"18","v":"29","i":4,"w":"παρῆλθεν","lemma":"παρέρχομαι","morph":"V.AAI3S"}],"παντοκρατορι":[{"book":"1Kgs","ch":"19","v":"10","i":7,"w":"παντοκράτορι","lemma":"παντοκράτωρ","morph":"N.DSM"},{"book":"1Kgs","ch":"19","v":"14","i":7,"w":"παντοκράτορι","lemma":"παντοκράτωρ","morph":"N.DSM"}],"παρελευσεται":[{"book":"1Kgs","ch":"19","v":"11","i":12,"w":"παρελεύσεται","lemma":"παρέρχομαι","morph":"V.FMI3S"}],"παρανομων":[{"book":"1Kgs","ch":"20","v":"10","i":5,"w":"παρανόμων","lemma":"παράνομος","morph":"A.GPM"},{"book":"1Kgs","ch":"20","v":"13","i":5,"w":"παρανόμων","lemma":"παράνομος","morph":"A.GPM"}],"παροργισματων":[{"book":"1Kgs","ch":"20","v":"22","i":20,"w":"παροργισμάτων","lemma":"παρόργισμα","morph":"N.GPM"}],"παρωργισασ":[{"book":"1Kgs","ch":"20","v":"22","i":22,"w":"παρώργισας","lemma":"παροργίζω","morph":"V.AAI2S"}],"παιδαριοισ":[{"book":"1Kgs","ch":"21","v":"14","i":12,"w":"παιδαρίοις","lemma":"παιδάριον","morph":"N.DPN"}],"παρενεβαλεν":[{"book":"1Kgs","ch":"21","v":"27","i":11,"w":"παρενέβαλεν","lemma":"παρεμβάλλω","morph":"V.AAI3S"}],"παρεμβαλλουσιν":[{"book":"1Kgs","ch":"21","v":"29","i":1,"w":"παρεμβάλλουσιν","lemma":"παρεμβάλλω","morph":"V.PAI3P"}],"παταξον":[{"book":"1Kgs","ch":"21","v":"35","i":16,"w":"πάταξον","lemma":"πατάσσω","morph":"V.AAD2S"},{"book":"1Kgs","ch":"21","v":"37","i":6,"w":"πάταξόν","lemma":"πατάσσω","morph":"V.AAD2S"}],"παταξει":[{"book":"1Kgs","ch":"21","v":"36","i":17,"w":"πατάξει","lemma":"πατάσσω","morph":"V.FAI3S"}],"παταξασ":[{"book":"1Kgs","ch":"21","v":"37","i":14,"w":"πατάξας","lemma":"πατάσσω","morph":"V.AAPNSM"}],"παρεπορευετο":[{"book":"1Kgs","ch":"21","v":"39","i":5,"w":"παρεπορεύετο","lemma":"παραπορεύομαι","morph":"V.IMI3S"}]}}