{"book":"EpJer","shard":"τι","tokens":{"τινι":[{"book":"EpJer","ch":"1","v":"17","i":2,"w":"τινὶ","lemma":"τις","morph":"P"},{"book":"EpJer","ch":"1","v":"51","i":0,"w":"τίνι","lemma":"τίς","morph":"N.ASM"}],"τισ":[{"book":"EpJer","ch":"1","v":"23","i":9,"w":"τις","lemma":"τις","morph":"X"},{"book":"EpJer","ch":"1","v":"26","i":2,"w":"τις","lemma":"τις","morph":"C"},{"book":"EpJer","ch":"1","v":"34","i":10,"w":"τις","lemma":"τις","morph":"V.AAS3P"},{"book":"EpJer","ch":"1","v":"43","i":2,"w":"τις","lemma":"τις","morph":"RA.ASF"}],"τιμησ":[{"book":"EpJer","ch":"1","v":"24","i":2,"w":"τιμῆς","lemma":"τιμή","morph":"P"}],"τινεσ":[{"book":"EpJer","ch":"1","v":"31","i":8,"w":"τινὲς","lemma":"τις","morph":"V.AMPNPM"}],"τινοσ":[{"book":"EpJer","ch":"1","v":"33","i":5,"w":"τινος","lemma":"τις","morph":"N.ASM"},{"book":"EpJer","ch":"1","v":"43","i":6,"w":"τινος","lemma":"τις","morph":"D"}]}}